[{"open":2e-8,"high":2e-8,"low":2e-8,"close":2e-8,"time":1681689582689,"volume":0,"ref":0.00000951},{"open":2e-8,"high":2e-8,"low":2e-8,"close":2e-8,"time":1681689607199,"volume":0,"ref":0.00000951},{"open":2e-8,"high":2e-8,"low":1e-8,"close":1e-8,"time":1681689663426,"volume":871.4,"ref":0.00000952},{"open":1e-8,"high":2e-8,"low":1e-8,"close":2e-8,"time":1681689721963,"volume":4710.6,"ref":0.00000952},{"open":2e-8,"high":2e-8,"low":1e-8,"close":1e-8,"time":1681689782455,"volume":1747.9,"ref":0.00000952},{"open":1e-8,"high":4e-8,"low":1e-8,"close":4e-8,"time":1681689841595,"volume":12972.2,"ref":0.00000949},{"open":4e-8,"high":4e-8,"low":3e-8,"close":3e-8,"time":1681689902856,"volume":17632.199999999997,"ref":0.0000095},{"open":3e-8,"high":3e-8,"low":3e-8,"close":3e-8,"time":1681689962899,"volume":964,"ref":0.0000095},{"open":3e-8,"high":3e-8,"low":3e-8,"close":3e-8,"time":1681690023334,"volume":1017.2,"ref":0.0000095},{"open":3e-8,"high":4e-8,"low":2e-8,"close":2e-8,"time":1681690083835,"volume":1236.7,"ref":0.0000095},{"open":2e-8,"high":5e-8,"low":1e-8,"close":4e-8,"time":1681690142620,"volume":9961.1,"ref":0.00000951},{"open":4e-8,"high":4e-8,"low":3e-8,"close":3e-8,"time":1681690203046,"volume":1293.5,"ref":0.00000951},{"open":3e-8,"high":4e-8,"low":2e-8,"close":3e-8,"time":1681690262807,"volume":10218.399999999998,"ref":0.00000952},{"open":3e-8,"high":3e-8,"low":2e-8,"close":2e-8,"time":1681690323571,"volume":5054.9,"ref":0.00000953},{"open":2e-8,"high":2e-8,"low":2e-8,"close":2e-8,"time":1681690382814,"volume":1352.8,"ref":0.00000953},{"open":2e-8,"high":2e-8,"low":1e-8,"close":1e-8,"time":1681690443301,"volume":2871.9,"ref":0.00000954},{"open":1e-8,"high":1e-8,"low":1e-8,"close":1e-8,"time":1681690503062,"volume":802.3999999999999,"ref":0.00000954},{"open":1e-8,"high":1e-8,"low":1e-8,"close":1e-8,"time":1681690563276,"volume":8346.2,"ref":0.00000954},{"open":1e-8,"high":1e-8,"low":1e-8,"close":1e-8,"time":1681690623278,"volume":3819.6,"ref":0.00000954},{"open":1e-8,"high":1e-8,"low":1e-8,"close":1e-8,"time":1681690683023,"volume":0,"ref":0.00000954}]