[{"open":0.1,"high":0.1,"low":0.1,"close":0.1,"time":1681516746574,"volume":1546.44,"ref":42.6},{"open":0.1,"high":0.1,"low":0.1,"close":0.1,"time":1681516801635,"volume":2249.53,"ref":42.5},{"open":0.1,"high":0.1,"low":0.1,"close":0.1,"time":1681516846854,"volume":1780.88,"ref":42.5},{"open":0.1,"high":0.1,"low":0.1,"close":0.1,"time":1681516907319,"volume":2491.27,"ref":42.5},{"open":0.1,"high":0.2,"low":0.1,"close":0.1,"time":1681516967075,"volume":10639.919999999998,"ref":42.4},{"open":0.1,"high":0.1,"low":0.1,"close":0.1,"time":1681517027937,"volume":2573.14,"ref":42.4},{"open":0.1,"high":0.1,"low":0.1,"close":0.1,"time":1681517087481,"volume":1929.03,"ref":42.4},{"open":0.1,"high":0.1,"low":0.1,"close":0.1,"time":1681517147577,"volume":512.17,"ref":42.4},{"open":0.1,"high":0.1,"low":0.1,"close":0.1,"time":1681517207608,"volume":419.38,"ref":42.4},{"open":0.1,"high":0.1,"low":0.1,"close":0.1,"time":1681517267870,"volume":10943.01,"ref":42.4},{"open":0.1,"high":0.1,"low":0.1,"close":0.1,"time":1681517327613,"volume":53212.060000000005,"ref":42.4},{"open":0.1,"high":0.1,"low":0.1,"close":0.1,"time":1681517387824,"volume":59855.459999999985,"ref":42.4},{"open":0.1,"high":0.1,"low":0.1,"close":0.1,"time":1681517447812,"volume":77341.44999999997,"ref":42.4},{"open":0.1,"high":0.1,"low":0.1,"close":0.1,"time":1681517507803,"volume":0,"ref":42.4}]