[{"open":1e-8,"high":1e-8,"low":1e-8,"close":1e-8,"time":1681603186955,"volume":63208,"ref":0.00000314},{"open":1e-8,"high":1e-8,"low":1e-8,"close":1e-8,"time":1681603246193,"volume":102869,"ref":0.00000314},{"open":1e-8,"high":1e-8,"low":1e-8,"close":1e-8,"time":1681603306192,"volume":82644,"ref":0.00000314},{"open":1e-8,"high":1e-8,"low":1e-8,"close":1e-8,"time":1681603366191,"volume":82644,"ref":0.00000314},{"open":1e-8,"high":1e-8,"low":1e-8,"close":1e-8,"time":1681603426193,"volume":124321,"ref":0.00000314},{"open":1e-8,"high":1e-8,"low":1e-8,"close":1e-8,"time":1681603486210,"volume":106712,"ref":0.00000314},{"open":1e-8,"high":1e-8,"low":1e-8,"close":1e-8,"time":1681603546210,"volume":89725,"ref":0.00000314},{"open":1e-8,"high":1e-8,"low":1e-8,"close":1e-8,"time":1681603606209,"volume":58097,"ref":0.00000314},{"open":1e-8,"high":1e-8,"low":1e-8,"close":1e-8,"time":1681603666207,"volume":59061,"ref":0.00000314},{"open":1e-8,"high":1e-8,"low":1e-8,"close":1e-8,"time":1681603726207,"volume":86780,"ref":0.00000314},{"open":1e-8,"high":1e-8,"low":1e-8,"close":1e-8,"time":1681603786207,"volume":86570,"ref":0.00000314},{"open":1e-8,"high":1e-8,"low":1e-8,"close":1e-8,"time":1681603846208,"volume":58580,"ref":0.00000314},{"open":1e-8,"high":1e-8,"low":1e-8,"close":1e-8,"time":1681603906369,"volume":47780,"ref":0.00000314},{"open":1e-8,"high":1e-8,"low":1e-8,"close":1e-8,"time":1681603966369,"volume":54971,"ref":0.00000314},{"open":1e-8,"high":1e-8,"low":1e-8,"close":1e-8,"time":1681604026369,"volume":62106,"ref":0.00000314},{"open":1e-8,"high":2e-8,"low":1e-8,"close":1e-8,"time":1681604086369,"volume":78546,"ref":0.00000315},{"open":1e-8,"high":1e-8,"low":1e-8,"close":1e-8,"time":1681604146404,"volume":12957,"ref":0.00000315},{"open":1e-8,"high":1e-8,"low":1e-8,"close":1e-8,"time":1681604549299,"volume":66916,"ref":0.00000315},{"open":1e-8,"high":1e-8,"low":1e-8,"close":1e-8,"time":1681604610011,"volume":63668,"ref":0.00000315},{"open":1e-8,"high":1e-8,"low":1e-8,"close":1e-8,"time":1681604670010,"volume":95677,"ref":0.00000315},{"open":1e-8,"high":1e-8,"low":1e-8,"close":1e-8,"time":1681604730011,"volume":65016,"ref":0.00000315},{"open":1e-8,"high":1e-8,"low":1e-8,"close":1e-8,"time":1681604790009,"volume":44670,"ref":0.00000315},{"open":1e-8,"high":1e-8,"low":1e-8,"close":1e-8,"time":1681604850010,"volume":35736,"ref":0.00000315},{"open":1e-8,"high":1e-8,"low":1e-8,"close":1e-8,"time":1681604910224,"volume":35736,"ref":0.00000315},{"open":1e-8,"high":1e-8,"low":1e-8,"close":1e-8,"time":1681604970223,"volume":44309,"ref":0.00000315},{"open":1e-8,"high":1e-8,"low":1e-8,"close":1e-8,"time":1681605030009,"volume":42112,"ref":0.00000315},{"open":1e-8,"high":1e-8,"low":1e-8,"close":1e-8,"time":1681605090225,"volume":42658,"ref":0.00000315},{"open":1e-8,"high":1e-8,"low":1e-8,"close":1e-8,"time":1681605150222,"volume":22767,"ref":0.00000315},{"open":1e-8,"high":2e-8,"low":1e-8,"close":1e-8,"time":1681605210170,"volume":66949,"ref":0.00000314},{"open":1e-8,"high":1e-8,"low":1e-8,"close":1e-8,"time":1681605270169,"volume":97339,"ref":0.00000314},{"open":1e-8,"high":1e-8,"low":1e-8,"close":1e-8,"time":1681605330182,"volume":38580,"ref":0.00000314},{"open":1e-8,"high":1e-8,"low":1e-8,"close":1e-8,"time":1681605390395,"volume":42796,"ref":0.00000314},{"open":1e-8,"high":1e-8,"low":1e-8,"close":1e-8,"time":1681605450182,"volume":13918,"ref":0.00000314},{"open":1e-8,"high":1e-8,"low":1e-8,"close":1e-8,"time":1681605510182,"volume":14945,"ref":0.00000314},{"open":1e-8,"high":1e-8,"low":1e-8,"close":1e-8,"time":1681605570625,"volume":14826,"ref":0.00000314},{"open":1e-8,"high":1e-8,"low":1e-8,"close":1e-8,"time":1681605630624,"volume":10184,"ref":0.00000314},{"open":1e-8,"high":1e-8,"low":1e-8,"close":1e-8,"time":1681605690622,"volume":10184,"ref":0.00000314},{"open":1e-8,"high":1e-8,"low":1e-8,"close":1e-8,"time":1681605750622,"volume":10184,"ref":0.00000314},{"open":1e-8,"high":1e-8,"low":1e-8,"close":1e-8,"time":1681605810878,"volume":9385,"ref":0.00000314},{"open":1e-8,"high":1e-8,"low":1e-8,"close":1e-8,"time":1681605870729,"volume":9053,"ref":0.00000314},{"open":1e-8,"high":1e-8,"low":1e-8,"close":1e-8,"time":1681605930731,"volume":4345,"ref":0.00000314},{"open":1e-8,"high":1e-8,"low":1e-8,"close":1e-8,"time":1681605990729,"volume":2607,"ref":0.00000314},{"open":1e-8,"high":1e-8,"low":1e-8,"close":1e-8,"time":1681606050727,"volume":3476,"ref":0.00000314},{"open":1e-8,"high":1e-8,"low":1e-8,"close":1e-8,"time":1681606111479,"volume":92473,"ref":0.00000314},{"open":1e-8,"high":1e-8,"low":1e-8,"close":1e-8,"time":1681606170820,"volume":98231,"ref":0.00000314},{"open":1e-8,"high":1e-8,"low":1e-8,"close":1e-8,"time":1681606230823,"volume":64836,"ref":0.00000314},{"open":1e-8,"high":1e-8,"low":1e-8,"close":1e-8,"time":1681606290822,"volume":91485,"ref":0.00000314},{"open":1e-8,"high":1e-8,"low":1e-8,"close":1e-8,"time":1681606350820,"volume":98060,"ref":0.00000314},{"open":1e-8,"high":1e-8,"low":1e-8,"close":1e-8,"time":1681606410832,"volume":97679,"ref":0.00000314},{"open":1e-8,"high":1e-8,"low":1e-8,"close":1e-8,"time":1681606470834,"volume":98026,"ref":0.00000314},{"open":1e-8,"high":1e-8,"low":1e-8,"close":1e-8,"time":1681606530833,"volume":92260,"ref":0.00000314},{"open":1e-8,"high":1e-8,"low":1e-8,"close":1e-8,"time":1681606590832,"volume":69056,"ref":0.00000314},{"open":1e-8,"high":1e-8,"low":1e-8,"close":1e-8,"time":1681606651048,"volume":51792,"ref":0.00000314},{"open":1e-8,"high":1e-8,"low":1e-8,"close":1e-8,"time":1681606711049,"volume":69056,"ref":0.00000314},{"open":1e-8,"high":1e-8,"low":1e-8,"close":1e-8,"time":1681606771046,"volume":139840,"ref":0.00000314},{"open":1e-8,"high":1e-8,"low":1e-8,"close":1e-8,"time":1681606831048,"volume":168947,"ref":0.00000314},{"open":1e-8,"high":1e-8,"low":1e-8,"close":1e-8,"time":1681606890861,"volume":111383,"ref":0.00000314},{"open":1e-8,"high":1e-8,"low":1e-8,"close":1e-8,"time":1681606950857,"volume":57652,"ref":0.00000314},{"open":1e-8,"high":1e-8,"low":1e-8,"close":1e-8,"time":1681607010870,"volume":105079,"ref":0.00000314},{"open":1e-8,"high":1e-8,"low":1e-8,"close":1e-8,"time":1681607070871,"volume":64460,"ref":0.00000314},{"open":1e-8,"high":1e-8,"low":1e-8,"close":1e-8,"time":1681607131088,"volume":80427,"ref":0.00000314},{"open":1e-8,"high":1e-8,"low":1e-8,"close":1e-8,"time":1681607191087,"volume":80835,"ref":0.00000314},{"open":1e-8,"high":1e-8,"low":1e-8,"close":1e-8,"time":1681607251111,"volume":64668,"ref":0.00000314},{"open":1e-8,"high":1e-8,"low":1e-8,"close":1e-8,"time":1681607311094,"volume":64668,"ref":0.00000314},{"open":1e-8,"high":1e-8,"low":1e-8,"close":1e-8,"time":1681607371084,"volume":64668,"ref":0.00000314},{"open":1e-8,"high":1e-8,"low":1e-8,"close":1e-8,"time":1681607431084,"volume":64564,"ref":0.00000314},{"open":1e-8,"high":2e-8,"low":1e-8,"close":2e-8,"time":1681607491097,"volume":131963,"ref":0.00000314},{"open":2e-8,"high":2e-8,"low":1e-8,"close":1e-8,"time":1681607551289,"volume":113923,"ref":0.00000315},{"open":1e-8,"high":2e-8,"low":1e-8,"close":2e-8,"time":1681607611505,"volume":56892,"ref":0.00000314},{"open":2e-8,"high":2e-8,"low":1e-8,"close":1e-8,"time":1681607672245,"volume":260644,"ref":0.00000314}]