[{"open":7e-8,"high":7e-8,"low":7e-8,"close":7e-8,"time":1681516751843,"volume":0,"ref":0.00004717},{"open":7e-8,"high":7e-8,"low":7e-8,"close":7e-8,"time":1681516802113,"volume":0,"ref":0.00004717},{"open":7e-8,"high":7e-8,"low":7e-8,"close":7e-8,"time":1681516847320,"volume":0,"ref":0.00004717},{"open":7e-8,"high":7e-8,"low":7e-8,"close":7e-8,"time":1681516907788,"volume":0,"ref":0.00004717},{"open":7e-8,"high":2.7e-7,"low":7e-8,"close":2.5e-7,"time":1681516967531,"volume":341.07,"ref":0.000047},{"open":2.5e-7,"high":2.5e-7,"low":2.5e-7,"close":2.5e-7,"time":1681517028212,"volume":0,"ref":0.000047},{"open":2.5e-7,"high":2.5e-7,"low":1.6e-7,"close":1.6e-7,"time":1681517087948,"volume":638.9099999999999,"ref":0.000047},{"open":1.6e-7,"high":1.6e-7,"low":6e-8,"close":6e-8,"time":1681517147857,"volume":59.4,"ref":0.000047},{"open":6e-8,"high":1.2e-7,"low":6e-8,"close":1.1e-7,"time":1681517207874,"volume":304.72,"ref":0.000047},{"open":1.1e-7,"high":1.5e-7,"low":7e-8,"close":8e-8,"time":1681517268343,"volume":593.1199999999999,"ref":0.000047},{"open":8e-8,"high":8e-8,"low":8e-8,"close":8e-8,"time":1681517328077,"volume":0,"ref":0.000047},{"open":8e-8,"high":8e-8,"low":8e-8,"close":8e-8,"time":1681517388300,"volume":230.35000000000002,"ref":0.000047},{"open":8e-8,"high":8e-8,"low":8e-8,"close":8e-8,"time":1681517448282,"volume":0,"ref":0.000047},{"open":8e-8,"high":1e-7,"low":6e-8,"close":6e-8,"time":1681517508072,"volume":737.74,"ref":0.000047},{"open":6e-8,"high":9e-8,"low":5e-8,"close":5e-8,"time":1681517568091,"volume":191.86,"ref":0.000047},{"open":5e-8,"high":1.7e-7,"low":5e-8,"close":1.6e-7,"time":1681517956887,"volume":217.59000000000003,"ref":0.00004697},{"open":1.6e-7,"high":1.6e-7,"low":1.6e-7,"close":1.6e-7,"time":1681518020939,"volume":0,"ref":0.00004697},{"open":1.6e-7,"high":1.6e-7,"low":1.6e-7,"close":1.6e-7,"time":1681518080229,"volume":0,"ref":0.00004697},{"open":1.6e-7,"high":1.6e-7,"low":1e-7,"close":1e-7,"time":1681518140240,"volume":92.81,"ref":0.00004697},{"open":1e-7,"high":1e-7,"low":9e-8,"close":9e-8,"time":1681518200392,"volume":104.55,"ref":0.00004697},{"open":9e-8,"high":1.1e-7,"low":9e-8,"close":1e-7,"time":1681518260399,"volume":914.64,"ref":0.00004695},{"open":1e-7,"high":1e-7,"low":6e-8,"close":1e-7,"time":1681518320162,"volume":290.52,"ref":0.00004695},{"open":1e-7,"high":1.9e-7,"low":6e-8,"close":8e-8,"time":1681518380618,"volume":1309.22,"ref":0.00004693},{"open":8e-8,"high":1.5e-7,"low":8e-8,"close":1.4e-7,"time":1681518440362,"volume":172.7,"ref":0.00004693},{"open":1.4e-7,"high":1.4e-7,"low":1.4e-7,"close":1.4e-7,"time":1681518501595,"volume":0,"ref":0.00004693},{"open":1.4e-7,"high":1.4e-7,"low":1.2e-7,"close":1.3e-7,"time":1681518561577,"volume":138.21,"ref":0.00004693},{"open":1.3e-7,"high":1.4e-7,"low":1.2e-7,"close":1.3e-7,"time":1681518621346,"volume":659.95,"ref":0.00004697},{"open":1.3e-7,"high":1.3e-7,"low":1.3e-7,"close":1.3e-7,"time":1681518681651,"volume":0,"ref":0.00004697},{"open":1.3e-7,"high":1.7e-7,"low":1.3e-7,"close":1.7e-7,"time":1681518741402,"volume":69.7,"ref":0.00004693},{"open":1.7e-7,"high":1.7e-7,"low":1e-8,"close":1e-8,"time":1681518801397,"volume":225.14000000000001,"ref":0.00004692},{"open":1e-8,"high":1.2e-7,"low":1e-8,"close":1.2e-7,"time":1681518861839,"volume":92.84,"ref":0.00004692},{"open":1.2e-7,"high":1.2e-7,"low":1.1e-7,"close":1.1e-7,"time":1681518921803,"volume":137.54000000000002,"ref":0.00004692},{"open":1.1e-7,"high":1.1e-7,"low":1.1e-7,"close":1.1e-7,"time":1681518982318,"volume":0,"ref":0.00004692},{"open":1.1e-7,"high":1.3e-7,"low":8e-8,"close":8e-8,"time":1681519041817,"volume":638.5699999999999,"ref":0.00004692},{"open":8e-8,"high":8e-8,"low":8e-8,"close":8e-8,"time":1681519102019,"volume":0,"ref":0.00004692},{"open":8e-8,"high":1e-7,"low":8e-8,"close":9e-8,"time":1681519162523,"volume":342.21000000000004,"ref":0.00004692},{"open":9e-8,"high":9e-8,"low":7e-8,"close":7e-8,"time":1681519222011,"volume":59.65,"ref":0.00004692},{"open":7e-8,"high":9e-8,"low":7e-8,"close":7e-8,"time":1681519282674,"volume":150.01,"ref":0.00004692},{"open":7e-8,"high":1.2e-7,"low":7e-8,"close":1e-7,"time":1681519342192,"volume":637.27,"ref":0.00004691},{"open":1e-7,"high":1.7e-7,"low":8e-8,"close":9e-8,"time":1681519402191,"volume":1796.19,"ref":0.0000469},{"open":9e-8,"high":1.7e-7,"low":3e-8,"close":4e-8,"time":1681519463420,"volume":1508.7199999999998,"ref":0.0000469},{"open":4e-8,"high":6e-8,"low":1e-8,"close":6e-8,"time":1681519523161,"volume":413.19,"ref":0.00004688},{"open":6e-8,"high":6e-8,"low":6e-8,"close":6e-8,"time":1681519583079,"volume":91.91,"ref":0.00004688},{"open":6e-8,"high":6e-8,"low":6e-8,"close":6e-8,"time":1681519643077,"volume":0,"ref":0.00004688},{"open":6e-8,"high":6e-8,"low":6e-8,"close":6e-8,"time":1681519702870,"volume":0,"ref":0.00004688},{"open":6e-8,"high":6e-8,"low":6e-8,"close":6e-8,"time":1681519764032,"volume":0,"ref":0.00004688},{"open":6e-8,"high":1.5e-7,"low":6e-8,"close":7e-8,"time":1681519823293,"volume":541.9999999999999,"ref":0.00004688},{"open":7e-8,"high":7e-8,"low":7e-8,"close":7e-8,"time":1681519883278,"volume":0,"ref":0.00004688},{"open":7e-8,"high":8e-8,"low":6e-8,"close":7e-8,"time":1681519943254,"volume":237.67,"ref":0.00004688},{"open":7e-8,"high":7e-8,"low":7e-8,"close":7e-8,"time":1681520003471,"volume":0,"ref":0.00004688},{"open":7e-8,"high":1e-7,"low":1e-8,"close":1e-7,"time":1681520063798,"volume":1103.8999999999999,"ref":0.00004685},{"open":1e-7,"high":1.4e-7,"low":3e-8,"close":1.4e-7,"time":1681520123549,"volume":1568.94,"ref":0.00004685},{"open":1.4e-7,"high":1.4e-7,"low":1.4e-7,"close":1.4e-7,"time":1681520184285,"volume":549.85,"ref":0.00004685},{"open":1.4e-7,"high":1.4e-7,"low":1.3e-7,"close":1.3e-7,"time":1681520244033,"volume":58.48,"ref":0.00004686},{"open":1.3e-7,"high":1.3e-7,"low":1.2e-7,"close":1.2e-7,"time":1681520304019,"volume":21.81,"ref":0.00004686},{"open":1.2e-7,"high":2e-7,"low":1.2e-7,"close":1.4e-7,"time":1681520364016,"volume":780.1600000000001,"ref":0.00004684},{"open":1.4e-7,"high":1.5e-7,"low":9e-8,"close":1.5e-7,"time":1681520424263,"volume":319.74,"ref":0.00004686},{"open":1.5e-7,"high":2.4e-7,"low":1e-7,"close":1.1e-7,"time":1681520484689,"volume":1434.9599999999998,"ref":0.00004699},{"open":1.1e-7,"high":1.1e-7,"low":8e-8,"close":8e-8,"time":1681520544186,"volume":949.3499999999999,"ref":0.00004698},{"open":8e-8,"high":8e-8,"low":7e-8,"close":8e-8,"time":1681520604284,"volume":304.38,"ref":0.00004698},{"open":8e-8,"high":1.4e-7,"low":7e-8,"close":1.2e-7,"time":1681520664267,"volume":1179.56,"ref":0.00004694},{"open":1.2e-7,"high":1.5e-7,"low":1e-7,"close":1.1e-7,"time":1681520724786,"volume":1758.5500000000002,"ref":0.00004696},{"open":1.1e-7,"high":1.3e-7,"low":9e-8,"close":1.1e-7,"time":1681520784517,"volume":1660.45,"ref":0.00004697},{"open":1.1e-7,"high":1.3e-7,"low":1e-7,"close":1.1e-7,"time":1681520844768,"volume":915.97,"ref":0.00004698},{"open":1.1e-7,"high":1.1e-7,"low":1.1e-7,"close":1.1e-7,"time":1681520904769,"volume":219.78,"ref":0.00004697},{"open":1.1e-7,"high":1.1e-7,"low":1.1e-7,"close":1.1e-7,"time":1681520964535,"volume":0,"ref":0.00004697},{"open":1.1e-7,"high":1.3e-7,"low":1e-7,"close":1.1e-7,"time":1681521024774,"volume":919.06,"ref":0.00004698},{"open":1.1e-7,"high":1.1e-7,"low":1.1e-7,"close":1.1e-7,"time":1681521084982,"volume":256.61,"ref":0.00004699},{"open":1.1e-7,"high":1.1e-7,"low":1.1e-7,"close":1.1e-7,"time":1681521144973,"volume":0,"ref":0.00004699},{"open":1.1e-7,"high":1.1e-7,"low":1.1e-7,"close":1.1e-7,"time":1681521256226,"volume":256.7,"ref":0.00004699},{"open":1.1e-7,"high":1.1e-7,"low":8e-8,"close":8e-8,"time":1681521312484,"volume":307.34,"ref":0.00004701},{"open":8e-8,"high":9e-8,"low":8e-8,"close":8e-8,"time":1681521371223,"volume":297.03,"ref":0.00004702},{"open":8e-8,"high":9e-8,"low":6e-8,"close":8e-8,"time":1681521431459,"volume":504.64,"ref":0.00004702},{"open":8e-8,"high":8e-8,"low":8e-8,"close":8e-8,"time":1681521491719,"volume":0,"ref":0.00004702},{"open":8e-8,"high":9e-8,"low":8e-8,"close":9e-8,"time":1681521551223,"volume":74.16,"ref":0.00004701},{"open":9e-8,"high":9e-8,"low":5e-8,"close":8e-8,"time":1681521611488,"volume":759.5300000000001,"ref":0.00004702},{"open":8e-8,"high":9e-8,"low":8e-8,"close":9e-8,"time":1681521669217,"volume":160.76999999999998,"ref":0.00004701},{"open":9e-8,"high":9e-8,"low":6e-8,"close":6e-8,"time":1681521730731,"volume":553.63,"ref":0.00004704},{"open":6e-8,"high":1.3e-7,"low":5e-8,"close":1.3e-7,"time":1681521785225,"volume":1126.22,"ref":0.00004704},{"open":1.3e-7,"high":1.3e-7,"low":4e-8,"close":1e-7,"time":1681521844978,"volume":1508.8199999999997,"ref":0.00004708},{"open":1e-7,"high":1e-7,"low":9e-8,"close":9e-8,"time":1681521911222,"volume":453.95000000000005,"ref":0.00004708},{"open":9e-8,"high":1.2e-7,"low":6e-8,"close":6e-8,"time":1681521965738,"volume":1372.05,"ref":0.00004712},{"open":6e-8,"high":9e-8,"low":6e-8,"close":8e-8,"time":1681522023965,"volume":366.11,"ref":0.00004711},{"open":8e-8,"high":8e-8,"low":8e-8,"close":8e-8,"time":1681522083730,"volume":0,"ref":0.00004711},{"open":8e-8,"high":1e-7,"low":8e-8,"close":8e-8,"time":1681522144193,"volume":344.20000000000005,"ref":0.00004711},{"open":8e-8,"high":2.1e-7,"low":8e-8,"close":1.4e-7,"time":1681522204185,"volume":1306.3200000000002,"ref":0.00004699},{"open":1.4e-7,"high":1.4e-7,"low":1.2e-7,"close":1.2e-7,"time":1681522264182,"volume":33.76,"ref":0.000047},{"open":1.2e-7,"high":1.2e-7,"low":1.2e-7,"close":1.2e-7,"time":1681522324408,"volume":0,"ref":0.000047},{"open":1.2e-7,"high":1.7e-7,"low":1.2e-7,"close":1.3e-7,"time":1681522384144,"volume":123.69,"ref":0.000047},{"open":1.3e-7,"high":1.4e-7,"low":1.2e-7,"close":1.2e-7,"time":1681522444155,"volume":194.98,"ref":0.00004699},{"open":1.2e-7,"high":1.5e-7,"low":1.2e-7,"close":1.5e-7,"time":1681522505157,"volume":494.61,"ref":0.00004696},{"open":1.5e-7,"high":1.5e-7,"low":1.5e-7,"close":1.5e-7,"time":1681522563659,"volume":280.62,"ref":0.00004696},{"open":1.5e-7,"high":1.5e-7,"low":1.1e-7,"close":1.1e-7,"time":1681522624428,"volume":687.81,"ref":0.00004704},{"open":1.1e-7,"high":1.2e-7,"low":1.1e-7,"close":1.2e-7,"time":1681522684168,"volume":196.88,"ref":0.00004704},{"open":1.2e-7,"high":1.2e-7,"low":1.2e-7,"close":1.2e-7,"time":1681522744433,"volume":0,"ref":0.00004704},{"open":1.2e-7,"high":1.5e-7,"low":7e-8,"close":7e-8,"time":1681522804423,"volume":355.21000000000004,"ref":0.00004703},{"open":7e-8,"high":1e-7,"low":7e-8,"close":8e-8,"time":1681522864422,"volume":251.9,"ref":0.00004702},{"open":8e-8,"high":1e-7,"low":4e-8,"close":6e-8,"time":1681522924659,"volume":711.2800000000001,"ref":0.00004704},{"open":6e-8,"high":1e-7,"low":5e-8,"close":1e-7,"time":1681522984405,"volume":1035.4,"ref":0.000047},{"open":1e-7,"high":1e-7,"low":1e-7,"close":1e-7,"time":1681523044407,"volume":110.3,"ref":0.000047},{"open":1e-7,"high":1e-7,"low":7e-8,"close":7e-8,"time":1681523104656,"volume":181.8,"ref":0.00004703},{"open":7e-8,"high":9e-8,"low":7e-8,"close":9e-8,"time":1681523164664,"volume":100.72,"ref":0.00004701},{"open":9e-8,"high":9e-8,"low":9e-8,"close":9e-8,"time":1681523224896,"volume":0,"ref":0.00004701},{"open":9e-8,"high":9e-8,"low":8e-8,"close":9e-8,"time":1681523284636,"volume":240.10000000000002,"ref":0.00004701},{"open":9e-8,"high":9e-8,"low":9e-8,"close":9e-8,"time":1681523344642,"volume":0,"ref":0.00004701},{"open":9e-8,"high":9e-8,"low":9e-8,"close":9e-8,"time":1681523405134,"volume":0,"ref":0.00004701},{"open":9e-8,"high":9e-8,"low":8e-8,"close":8e-8,"time":1681523465121,"volume":77.56,"ref":0.00004702},{"open":8e-8,"high":9e-8,"low":8e-8,"close":8e-8,"time":1681523525342,"volume":314.34000000000003,"ref":0.00004702},{"open":8e-8,"high":9e-8,"low":8e-8,"close":8e-8,"time":1681523584850,"volume":244.13,"ref":0.00004702},{"open":8e-8,"high":8e-8,"low":7e-8,"close":7e-8,"time":1681523644861,"volume":34.3,"ref":0.00004703},{"open":7e-8,"high":8e-8,"low":7e-8,"close":8e-8,"time":1681523705355,"volume":68.6,"ref":0.00004702},{"open":8e-8,"high":8e-8,"low":4e-8,"close":4e-8,"time":1681523764869,"volume":582.0799999999999,"ref":0.00004706},{"open":4e-8,"high":7e-8,"low":4e-8,"close":5e-8,"time":1681523825109,"volume":844.3400000000001,"ref":0.00004707},{"open":5e-8,"high":9e-8,"low":5e-8,"close":5e-8,"time":1681523885450,"volume":588.33,"ref":0.00004707},{"open":5e-8,"high":1.2e-7,"low":3e-8,"close":9e-8,"time":1681523945193,"volume":739.84,"ref":0.00004704},{"open":9e-8,"high":9e-8,"low":3e-8,"close":6e-8,"time":1681524005697,"volume":518.76,"ref":0.00004707},{"open":6e-8,"high":6e-8,"low":6e-8,"close":6e-8,"time":1681524065200,"volume":66.75,"ref":0.00004707},{"open":6e-8,"high":2.2e-7,"low":6e-8,"close":1.2e-7,"time":1681524125194,"volume":631.1399999999999,"ref":0.000047},{"open":1.2e-7,"high":1.3e-7,"low":1e-7,"close":1e-7,"time":1681524185402,"volume":425.2,"ref":0.00004703},{"open":1e-7,"high":1e-7,"low":1e-7,"close":1e-7,"time":1681524245429,"volume":0,"ref":0.00004703},{"open":1e-7,"high":1.2e-7,"low":6e-8,"close":8e-8,"time":1681524305409,"volume":1013.1600000000001,"ref":0.00004708},{"open":8e-8,"high":9e-8,"low":5e-8,"close":5e-8,"time":1681524365171,"volume":869,"ref":0.00004709},{"open":5e-8,"high":8e-8,"low":5e-8,"close":5e-8,"time":1681524425900,"volume":519.35,"ref":0.00004709},{"open":5e-8,"high":8e-8,"low":3e-8,"close":8e-8,"time":1681524485672,"volume":742.33,"ref":0.00004706},{"open":8e-8,"high":8e-8,"low":6e-8,"close":6e-8,"time":1681524545422,"volume":99.71000000000001,"ref":0.00004706},{"open":6e-8,"high":1.2e-7,"low":5e-8,"close":1.1e-7,"time":1681524605662,"volume":935.71,"ref":0.000047},{"open":1.1e-7,"high":1.2e-7,"low":1.1e-7,"close":1.2e-7,"time":1681524665906,"volume":119.21000000000001,"ref":0.000047},{"open":1.2e-7,"high":1.7e-7,"low":1.2e-7,"close":1.4e-7,"time":1681524725666,"volume":208.2,"ref":0.00004698},{"open":1.4e-7,"high":1.4e-7,"low":1.4e-7,"close":1.4e-7,"time":1681524785862,"volume":0,"ref":0.00004698},{"open":1.4e-7,"high":1.7e-7,"low":1.4e-7,"close":1.5e-7,"time":1681524845752,"volume":222.87,"ref":0.00004697},{"open":1.5e-7,"high":1.5e-7,"low":7e-8,"close":7e-8,"time":1681524905958,"volume":110.56,"ref":0.00004705},{"open":7e-8,"high":7e-8,"low":7e-8,"close":7e-8,"time":1681524965953,"volume":0,"ref":0.00004705},{"open":7e-8,"high":7e-8,"low":7e-8,"close":7e-8,"time":1681525025970,"volume":75.55,"ref":0.00004705},{"open":7e-8,"high":7e-8,"low":7e-8,"close":7e-8,"time":1681525086429,"volume":0,"ref":0.00004705},{"open":7e-8,"high":7e-8,"low":6e-8,"close":6e-8,"time":1681525146192,"volume":56.86,"ref":0.00004706},{"open":6e-8,"high":1e-7,"low":6e-8,"close":1e-7,"time":1681525206432,"volume":337.28000000000003,"ref":0.00004702},{"open":1e-7,"high":1e-7,"low":1e-7,"close":1e-7,"time":1681525266205,"volume":65.72,"ref":0.00004702},{"open":1e-7,"high":1.3e-7,"low":1e-7,"close":1.1e-7,"time":1681525326179,"volume":242.59,"ref":0.00004701},{"open":1.1e-7,"high":1.3e-7,"low":1.1e-7,"close":1.3e-7,"time":1681525386250,"volume":18.73,"ref":0.00004699},{"open":1.3e-7,"high":1.3e-7,"low":9e-8,"close":9e-8,"time":1681525446025,"volume":120.74,"ref":0.00004703},{"open":9e-8,"high":1.9e-7,"low":9e-8,"close":1.5e-7,"time":1681525506025,"volume":548.8199999999999,"ref":0.00004696},{"open":1.5e-7,"high":1.8e-7,"low":1.5e-7,"close":1.5e-7,"time":1681525566271,"volume":311.24,"ref":0.00004696},{"open":1.5e-7,"high":1.8e-7,"low":1.4e-7,"close":1.4e-7,"time":1681525626018,"volume":301.87,"ref":0.00004697},{"open":1.4e-7,"high":1.5e-7,"low":1.3e-7,"close":1.5e-7,"time":1681525686329,"volume":197.02,"ref":0.00004695},{"open":1.5e-7,"high":1.9e-7,"low":1.5e-7,"close":1.9e-7,"time":1681525746578,"volume":44.18,"ref":0.00004695},{"open":1.9e-7,"high":2e-7,"low":1.3e-7,"close":2e-7,"time":1681525806337,"volume":710.8,"ref":0.0000469},{"open":2e-7,"high":2e-7,"low":1.7e-7,"close":1.9e-7,"time":1681525866325,"volume":771.41,"ref":0.00004691},{"open":1.9e-7,"high":2.2e-7,"low":1.9e-7,"close":1.9e-7,"time":1681525926325,"volume":537.1500000000001,"ref":0.00004691},{"open":1.9e-7,"high":1.9e-7,"low":1.6e-7,"close":1.6e-7,"time":1681525986328,"volume":732.56,"ref":0.00004692},{"open":1.6e-7,"high":1.7e-7,"low":1.3e-7,"close":1.3e-7,"time":1681526046562,"volume":393.5,"ref":0.00004695},{"open":1.3e-7,"high":1.8e-7,"low":1.3e-7,"close":1.7e-7,"time":1681526106339,"volume":646.12,"ref":0.00004691},{"open":1.7e-7,"high":1.7e-7,"low":1.3e-7,"close":1.6e-7,"time":1681526166326,"volume":151.76999999999998,"ref":0.00004695},{"open":1.6e-7,"high":1.7e-7,"low":1.5e-7,"close":1.5e-7,"time":1681526226566,"volume":205.3,"ref":0.00004699},{"open":1.5e-7,"high":1.5e-7,"low":1.5e-7,"close":1.5e-7,"time":1681526286333,"volume":0,"ref":0.00004699},{"open":1.5e-7,"high":1.5e-7,"low":1.5e-7,"close":1.5e-7,"time":1681526346872,"volume":0,"ref":0.00004699},{"open":1.5e-7,"high":1.8e-7,"low":1.5e-7,"close":1.8e-7,"time":1681526406382,"volume":166.05,"ref":0.00004696},{"open":1.8e-7,"high":1.8e-7,"low":1.2e-7,"close":1.2e-7,"time":1681526466630,"volume":225.68,"ref":0.00004701},{"open":1.2e-7,"high":1.5e-7,"low":1.2e-7,"close":1.5e-7,"time":1681526526866,"volume":262.82,"ref":0.00004698},{"open":1.5e-7,"high":2e-7,"low":1.5e-7,"close":1.6e-7,"time":1681526586869,"volume":1774.8,"ref":0.0000469},{"open":1.6e-7,"high":1.6e-7,"low":1.6e-7,"close":1.6e-7,"time":1681526646623,"volume":866.13,"ref":0.0000469},{"open":1.6e-7,"high":1.6e-7,"low":1.6e-7,"close":1.6e-7,"time":1681526707094,"volume":0,"ref":0.0000469},{"open":1.6e-7,"high":1.6e-7,"low":1.6e-7,"close":1.6e-7,"time":1681526766847,"volume":0,"ref":0.0000469},{"open":1.6e-7,"high":1.6e-7,"low":1.6e-7,"close":1.6e-7,"time":1681526826841,"volume":530.84,"ref":0.0000469},{"open":1.6e-7,"high":1.6e-7,"low":1.5e-7,"close":1.5e-7,"time":1681526886915,"volume":123.94,"ref":0.0000469},{"open":1.5e-7,"high":1.5e-7,"low":1.5e-7,"close":1.5e-7,"time":1681526946686,"volume":0,"ref":0.0000469},{"open":1.5e-7,"high":1.5e-7,"low":1.5e-7,"close":1.5e-7,"time":1681527006907,"volume":0,"ref":0.0000469},{"open":1.5e-7,"high":1.5e-7,"low":1.5e-7,"close":1.5e-7,"time":1681527066907,"volume":468.32,"ref":0.0000469},{"open":1.5e-7,"high":1.5e-7,"low":1.5e-7,"close":1.5e-7,"time":1681527126664,"volume":0,"ref":0.0000469},{"open":1.5e-7,"high":1.5e-7,"low":1.5e-7,"close":1.5e-7,"time":1681527186666,"volume":294.28999999999996,"ref":0.0000469},{"open":1.5e-7,"high":1.5e-7,"low":1.5e-7,"close":1.5e-7,"time":1681527246928,"volume":123.94,"ref":0.0000469},{"open":1.5e-7,"high":1.5e-7,"low":1.5e-7,"close":1.5e-7,"time":1681527306919,"volume":0,"ref":0.0000469},{"open":1.5e-7,"high":1.5e-7,"low":1.2e-7,"close":1.2e-7,"time":1681527366935,"volume":425.41,"ref":0.00004693},{"open":1.2e-7,"high":1.7e-7,"low":1.2e-7,"close":1.4e-7,"time":1681527426920,"volume":705.91,"ref":0.00004695},{"open":1.4e-7,"high":1.7e-7,"low":1.4e-7,"close":1.7e-7,"time":1681527486935,"volume":115.17,"ref":0.00004692},{"open":1.7e-7,"high":1.7e-7,"low":1.7e-7,"close":1.7e-7,"time":1681527546681,"volume":159.73,"ref":0.00004693},{"open":1.7e-7,"high":2.1e-7,"low":1.7e-7,"close":1.8e-7,"time":1681527607167,"volume":589.9300000000001,"ref":0.00004693},{"open":1.8e-7,"high":1.8e-7,"low":1.8e-7,"close":1.8e-7,"time":1681527667135,"volume":242.12,"ref":0.00004693},{"open":1.8e-7,"high":2e-7,"low":1.4e-7,"close":1.7e-7,"time":1681527727362,"volume":1498.29,"ref":0.0000469},{"open":1.7e-7,"high":1.7e-7,"low":1.7e-7,"close":1.7e-7,"time":1681527787130,"volume":0,"ref":0.0000469},{"open":1.7e-7,"high":1.7e-7,"low":1.7e-7,"close":1.7e-7,"time":1681527847362,"volume":181.3,"ref":0.0000469},{"open":1.7e-7,"high":1.7e-7,"low":1.7e-7,"close":1.7e-7,"time":1681527907378,"volume":0,"ref":0.0000469},{"open":1.7e-7,"high":1.7e-7,"low":1.2e-7,"close":1.6e-7,"time":1681527969873,"volume":506.53,"ref":0.0000469},{"open":1.6e-7,"high":1.9e-7,"low":1.6e-7,"close":1.8e-7,"time":1681528031614,"volume":602.86,"ref":0.00004695},{"open":1.8e-7,"high":1.8e-7,"low":1.8e-7,"close":1.8e-7,"time":1681528087366,"volume":225.23,"ref":0.0000469},{"open":1.8e-7,"high":1.9e-7,"low":1.7e-7,"close":1.7e-7,"time":1681528147359,"volume":396.65,"ref":0.00004694},{"open":1.7e-7,"high":1.7e-7,"low":1.7e-7,"close":1.7e-7,"time":1681528207637,"volume":0,"ref":0.00004694},{"open":1.7e-7,"high":1.9e-7,"low":1.7e-7,"close":1.7e-7,"time":1681528267582,"volume":385.27000000000004,"ref":0.00004695},{"open":1.7e-7,"high":1.7e-7,"low":1.7e-7,"close":1.7e-7,"time":1681528327328,"volume":0,"ref":0.00004695},{"open":1.7e-7,"high":1.7e-7,"low":1.7e-7,"close":1.7e-7,"time":1681528387319,"volume":108.13,"ref":0.00004695},{"open":1.7e-7,"high":1.9e-7,"low":1.5e-7,"close":1.5e-7,"time":1681528454466,"volume":451.62,"ref":0.00004699},{"open":1.5e-7,"high":1.5e-7,"low":1.5e-7,"close":1.5e-7,"time":1681528516180,"volume":85.42,"ref":0.00004699},{"open":1.5e-7,"high":1.5e-7,"low":1.4e-7,"close":1.4e-7,"time":1681528575684,"volume":232.82,"ref":0.00004699},{"open":1.4e-7,"high":1.5e-7,"low":1e-7,"close":1.2e-7,"time":1681528637939,"volume":1196.0499999999997,"ref":0.00004699},{"open":1.2e-7,"high":1.2e-7,"low":1.2e-7,"close":1.2e-7,"time":1681528696412,"volume":0,"ref":0.00004699},{"open":1.2e-7,"high":1.2e-7,"low":1.2e-7,"close":1.2e-7,"time":1681528756416,"volume":0,"ref":0.00004699},{"open":1.2e-7,"high":1.2e-7,"low":1.2e-7,"close":1.2e-7,"time":1681528816167,"volume":0,"ref":0.00004699},{"open":1.2e-7,"high":1.2e-7,"low":1.2e-7,"close":1.2e-7,"time":1681528876412,"volume":85,"ref":0.00004699},{"open":1.2e-7,"high":1.2e-7,"low":1.2e-7,"close":1.2e-7,"time":1681528936403,"volume":134.13,"ref":0.00004699},{"open":1.2e-7,"high":1.2e-7,"low":1.2e-7,"close":1.2e-7,"time":1681528996401,"volume":85,"ref":0.00004699},{"open":1.2e-7,"high":1.2e-7,"low":1.2e-7,"close":1.2e-7,"time":1681529056393,"volume":0,"ref":0.00004699},{"open":1.2e-7,"high":1.4e-7,"low":1.2e-7,"close":1.4e-7,"time":1681529116872,"volume":157.69,"ref":0.000047},{"open":1.4e-7,"high":1.4e-7,"low":1.1e-7,"close":1.1e-7,"time":1681529176636,"volume":1280.26,"ref":0.00004702},{"open":1.1e-7,"high":1.2e-7,"low":1e-7,"close":1.2e-7,"time":1681529236622,"volume":303.35,"ref":0.000047},{"open":1.2e-7,"high":1.2e-7,"low":1.1e-7,"close":1.1e-7,"time":1681529296620,"volume":180,"ref":0.00004701},{"open":1.1e-7,"high":1.2e-7,"low":9e-8,"close":9e-8,"time":1681529357088,"volume":171.29,"ref":0.00004705},{"open":9e-8,"high":1.2e-7,"low":9e-8,"close":9e-8,"time":1681529417593,"volume":197.85,"ref":0.00004705},{"open":9e-8,"high":9e-8,"low":9e-8,"close":9e-8,"time":1681529477092,"volume":0,"ref":0.00004705},{"open":9e-8,"high":9e-8,"low":8e-8,"close":8e-8,"time":1681529536854,"volume":77.75,"ref":0.00004706},{"open":8e-8,"high":8e-8,"low":7e-8,"close":7e-8,"time":1681529597091,"volume":77.57,"ref":0.00004707},{"open":7e-8,"high":1.2e-7,"low":5e-8,"close":1e-7,"time":1681529657300,"volume":204.42000000000002,"ref":0.00004703},{"open":1e-7,"high":1e-7,"low":1e-7,"close":1e-7,"time":1681529717288,"volume":0,"ref":0.00004703},{"open":1e-7,"high":1.8e-7,"low":9e-8,"close":1.5e-7,"time":1681529777294,"volume":1018.1500000000001,"ref":0.00004695},{"open":1.5e-7,"high":1.5e-7,"low":1.1e-7,"close":1.1e-7,"time":1681529837289,"volume":822.16,"ref":0.00004695},{"open":1.1e-7,"high":1.1e-7,"low":1.1e-7,"close":1.1e-7,"time":1681529897294,"volume":0,"ref":0.00004695},{"open":1.1e-7,"high":1.1e-7,"low":1.1e-7,"close":1.1e-7,"time":1681529957549,"volume":0,"ref":0.00004695},{"open":1.1e-7,"high":1.1e-7,"low":1e-7,"close":1e-7,"time":1681530017549,"volume":164.56,"ref":0.00004695},{"open":1e-7,"high":1.3e-7,"low":1e-7,"close":1.3e-7,"time":1681530077303,"volume":214.01999999999998,"ref":0.00004695},{"open":1.3e-7,"high":1.3e-7,"low":1e-7,"close":1e-7,"time":1681530137324,"volume":480.17999999999995,"ref":0.00004696},{"open":1e-7,"high":1.6e-7,"low":9e-8,"close":1.4e-7,"time":1681530197307,"volume":331.31999999999994,"ref":0.00004693},{"open":1.4e-7,"high":1.7e-7,"low":1.1e-7,"close":1.5e-7,"time":1681530257546,"volume":940.14,"ref":0.00004696},{"open":1.5e-7,"high":1.5e-7,"low":1.5e-7,"close":1.5e-7,"time":1681530317788,"volume":0,"ref":0.00004696},{"open":1.5e-7,"high":1.5e-7,"low":1.3e-7,"close":1.3e-7,"time":1681530378027,"volume":357.18,"ref":0.00004698},{"open":1.3e-7,"high":1.3e-7,"low":3e-8,"close":3e-8,"time":1681530437779,"volume":4302.21,"ref":0.00004709},{"open":3e-8,"high":1.9e-7,"low":3e-8,"close":1e-7,"time":1681530497544,"volume":10940.560000000003,"ref":0.00004683},{"open":1e-7,"high":1e-7,"low":9e-8,"close":9e-8,"time":1681530557420,"volume":418.36999999999995,"ref":0.00004682},{"open":9e-8,"high":9e-8,"low":9e-8,"close":9e-8,"time":1681530618677,"volume":0,"ref":0.00004682},{"open":9e-8,"high":1e-7,"low":9e-8,"close":1e-7,"time":1681530677913,"volume":120.61,"ref":0.00004682},{"open":1e-7,"high":1.2e-7,"low":8e-8,"close":1.1e-7,"time":1681530738142,"volume":374.13,"ref":0.00004683},{"open":1.1e-7,"high":2e-7,"low":1.1e-7,"close":2e-7,"time":1681530798164,"volume":236.43,"ref":0.00004684},{"open":2e-7,"high":2e-7,"low":1.3e-7,"close":1.3e-7,"time":1681530857909,"volume":657.4200000000001,"ref":0.00004684},{"open":1.3e-7,"high":1.7e-7,"low":1.2e-7,"close":1.2e-7,"time":1681530918152,"volume":426.13,"ref":0.00004684},{"open":1.2e-7,"high":1.2e-7,"low":1.2e-7,"close":1.2e-7,"time":1681530978345,"volume":0,"ref":0.00004684},{"open":1.2e-7,"high":1.2e-7,"low":1.2e-7,"close":1.2e-7,"time":1681531038351,"volume":0,"ref":0.00004684},{"open":1.2e-7,"high":1.7e-7,"low":1.2e-7,"close":1.5e-7,"time":1681531098868,"volume":1364.8899999999999,"ref":0.00004691},{"open":1.5e-7,"high":1.6e-7,"low":1.5e-7,"close":1.6e-7,"time":1681531158594,"volume":184.94,"ref":0.00004688},{"open":1.6e-7,"high":1.7e-7,"low":1.5e-7,"close":1.7e-7,"time":1681531218600,"volume":544.99,"ref":0.00004688},{"open":1.7e-7,"high":1.7e-7,"low":1.4e-7,"close":1.6e-7,"time":1681531278607,"volume":545.1199999999999,"ref":0.00004688},{"open":1.6e-7,"high":1.6e-7,"low":8e-8,"close":9e-8,"time":1681531339072,"volume":1663.6999999999998,"ref":0.00004683},{"open":9e-8,"high":1.2e-7,"low":8e-8,"close":8e-8,"time":1681531398568,"volume":1300.75,"ref":0.00004684},{"open":8e-8,"high":8e-8,"low":8e-8,"close":8e-8,"time":1681531458557,"volume":0,"ref":0.00004684},{"open":8e-8,"high":8e-8,"low":8e-8,"close":8e-8,"time":1681531519307,"volume":0,"ref":0.00004684},{"open":8e-8,"high":8e-8,"low":8e-8,"close":8e-8,"time":1681531578811,"volume":0,"ref":0.00004684},{"open":8e-8,"high":1.2e-7,"low":7e-8,"close":7e-8,"time":1681531639303,"volume":909.0500000000002,"ref":0.00004683},{"open":7e-8,"high":8e-8,"low":7e-8,"close":8e-8,"time":1681531698801,"volume":157.69,"ref":0.00004683},{"open":8e-8,"high":8e-8,"low":8e-8,"close":8e-8,"time":1681531758810,"volume":0,"ref":0.00004683},{"open":8e-8,"high":8e-8,"low":7e-8,"close":7e-8,"time":1681531819771,"volume":157.69,"ref":0.00004683},{"open":7e-8,"high":2.5e-7,"low":7e-8,"close":9e-8,"time":1681531879270,"volume":516.6,"ref":0.00004685},{"open":9e-8,"high":1e-7,"low":9e-8,"close":1e-7,"time":1681531939041,"volume":246.7,"ref":0.00004683},{"open":1e-7,"high":1e-7,"low":1e-7,"close":1e-7,"time":1681531999532,"volume":0,"ref":0.00004683},{"open":1e-7,"high":1e-7,"low":1e-7,"close":1e-7,"time":1681532144029,"volume":0,"ref":0.00004683},{"open":1e-7,"high":1.4e-7,"low":1e-7,"close":1.4e-7,"time":1681532195280,"volume":529.01,"ref":0.00004682},{"open":1.4e-7,"high":1.4e-7,"low":6e-8,"close":6e-8,"time":1681532254028,"volume":998.95,"ref":0.00004681},{"open":6e-8,"high":6e-8,"low":4e-8,"close":4e-8,"time":1681532314032,"volume":140.73,"ref":0.00004683},{"open":4e-8,"high":4e-8,"low":4e-8,"close":4e-8,"time":1681532374031,"volume":0,"ref":0.00004683},{"open":4e-8,"high":4e-8,"low":4e-8,"close":4e-8,"time":1681532434025,"volume":0,"ref":0.00004683},{"open":4e-8,"high":4e-8,"low":4e-8,"close":4e-8,"time":1681532494503,"volume":0,"ref":0.00004683},{"open":4e-8,"high":1.2e-7,"low":4e-8,"close":1.1e-7,"time":1681532554016,"volume":519.12,"ref":0.00004681},{"open":1.1e-7,"high":1.1e-7,"low":9e-8,"close":1e-7,"time":1681532614247,"volume":371.53,"ref":0.00004683},{"open":1e-7,"high":1e-7,"low":9e-8,"close":9e-8,"time":1681532674026,"volume":242.63,"ref":0.00004684},{"open":9e-8,"high":9e-8,"low":9e-8,"close":9e-8,"time":1681532734524,"volume":0,"ref":0.00004684},{"open":9e-8,"high":1e-7,"low":9e-8,"close":1e-7,"time":1681532794246,"volume":408.22999999999996,"ref":0.00004683},{"open":1e-7,"high":1.3e-7,"low":1e-7,"close":1.2e-7,"time":1681532854249,"volume":281.25,"ref":0.00004683},{"open":1.2e-7,"high":1.2e-7,"low":8e-8,"close":8e-8,"time":1681532914249,"volume":488.65,"ref":0.00004682},{"open":8e-8,"high":1.9e-7,"low":8e-8,"close":1.2e-7,"time":1681532974705,"volume":722.9,"ref":0.00004681},{"open":1.2e-7,"high":1.6e-7,"low":8e-8,"close":8e-8,"time":1681533034443,"volume":296.28999999999996,"ref":0.00004687},{"open":8e-8,"high":1.4e-7,"low":8e-8,"close":1.2e-7,"time":1681533094450,"volume":129.97,"ref":0.00004683},{"open":1.2e-7,"high":1.2e-7,"low":1.2e-7,"close":1.2e-7,"time":1681533154926,"volume":0,"ref":0.00004683},{"open":1.2e-7,"high":1.2e-7,"low":1.1e-7,"close":1.1e-7,"time":1681533214923,"volume":20.56,"ref":0.00004682},{"open":1.1e-7,"high":1.3e-7,"low":1.1e-7,"close":1.2e-7,"time":1681533274912,"volume":137.57999999999998,"ref":0.00004681},{"open":1.2e-7,"high":1.2e-7,"low":7e-8,"close":7e-8,"time":1681533334910,"volume":269.04,"ref":0.00004681},{"open":7e-8,"high":1.1e-7,"low":7e-8,"close":8e-8,"time":1681533394677,"volume":642.75,"ref":0.00004681},{"open":8e-8,"high":8e-8,"low":6e-8,"close":6e-8,"time":1681533454833,"volume":174.37,"ref":0.00004681},{"open":6e-8,"high":1.5e-7,"low":6e-8,"close":7e-8,"time":1681533519077,"volume":920.5900000000001,"ref":0.00004682},{"open":7e-8,"high":8e-8,"low":5e-8,"close":8e-8,"time":1681533574835,"volume":166.53,"ref":0.00004682},{"open":8e-8,"high":1.3e-7,"low":8e-8,"close":1e-7,"time":1681533634833,"volume":513.98,"ref":0.0000468},{"open":1e-7,"high":1e-7,"low":1e-7,"close":1e-7,"time":1681533694841,"volume":0,"ref":0.0000468},{"open":1e-7,"high":1.6e-7,"low":9e-8,"close":1e-7,"time":1681533754836,"volume":467.68,"ref":0.00004681},{"open":1e-7,"high":1.5e-7,"low":9e-8,"close":9e-8,"time":1681533815502,"volume":723.15,"ref":0.00004681},{"open":9e-8,"high":9e-8,"low":9e-8,"close":9e-8,"time":1681533875274,"volume":179.21,"ref":0.00004681},{"open":9e-8,"high":1e-7,"low":9e-8,"close":1e-7,"time":1681533935261,"volume":593.34,"ref":0.0000468},{"open":1e-7,"high":1e-7,"low":8e-8,"close":8e-8,"time":1681533995025,"volume":236.44,"ref":0.0000468},{"open":8e-8,"high":1e-7,"low":8e-8,"close":8e-8,"time":1681534055245,"volume":167.44,"ref":0.0000468},{"open":8e-8,"high":1.2e-7,"low":8e-8,"close":1.2e-7,"time":1681534115253,"volume":372.56,"ref":0.00004681},{"open":1.2e-7,"high":1.6e-7,"low":3e-8,"close":5e-8,"time":1681534175257,"volume":1685.9100000000003,"ref":0.00004677},{"open":5e-8,"high":5e-8,"low":4e-8,"close":4e-8,"time":1681534235254,"volume":18.91,"ref":0.00004677},{"open":4e-8,"high":5e-8,"low":4e-8,"close":5e-8,"time":1681534295946,"volume":93.55,"ref":0.00004677},{"open":5e-8,"high":1.2e-7,"low":3e-8,"close":3e-8,"time":1681534355474,"volume":151.28,"ref":0.00004677},{"open":3e-8,"high":3e-8,"low":3e-8,"close":3e-8,"time":1681534415455,"volume":0,"ref":0.00004677},{"open":3e-8,"high":3e-8,"low":3e-8,"close":3e-8,"time":1681534475458,"volume":0,"ref":0.00004677},{"open":3e-8,"high":3e-8,"low":3e-8,"close":3e-8,"time":1681534535465,"volume":0,"ref":0.00004677},{"open":3e-8,"high":3e-8,"low":3e-8,"close":3e-8,"time":1681534595693,"volume":0,"ref":0.00004677},{"open":3e-8,"high":3e-8,"low":3e-8,"close":3e-8,"time":1681534655939,"volume":0,"ref":0.00004677},{"open":3e-8,"high":3e-8,"low":3e-8,"close":3e-8,"time":1681534715684,"volume":0,"ref":0.00004677},{"open":3e-8,"high":3e-8,"low":3e-8,"close":3e-8,"time":1681534775691,"volume":0,"ref":0.00004677},{"open":3e-8,"high":6e-8,"low":3e-8,"close":6e-8,"time":1681534835924,"volume":140.43,"ref":0.00004677},{"open":6e-8,"high":9e-8,"low":6e-8,"close":7e-8,"time":1681534896131,"volume":203.04,"ref":0.00004684},{"open":7e-8,"high":7e-8,"low":7e-8,"close":7e-8,"time":1681534956103,"volume":0,"ref":0.00004684},{"open":7e-8,"high":1.5e-7,"low":7e-8,"close":1.3e-7,"time":1681535015878,"volume":669.95,"ref":0.00004687},{"open":1.3e-7,"high":1.4e-7,"low":1.3e-7,"close":1.3e-7,"time":1681535075874,"volume":331.64,"ref":0.00004684},{"open":1.3e-7,"high":1.3e-7,"low":1.3e-7,"close":1.3e-7,"time":1681535135876,"volume":0,"ref":0.00004684},{"open":1.3e-7,"high":1.4e-7,"low":1.1e-7,"close":1.1e-7,"time":1681535196106,"volume":305.11,"ref":0.00004683},{"open":1.1e-7,"high":1.7e-7,"low":1.1e-7,"close":1.2e-7,"time":1681535256550,"volume":768.3399999999999,"ref":0.00004682},{"open":1.2e-7,"high":1.2e-7,"low":1.2e-7,"close":1.2e-7,"time":1681535316321,"volume":0,"ref":0.00004682},{"open":1.2e-7,"high":1.2e-7,"low":1.2e-7,"close":1.2e-7,"time":1681535376314,"volume":81.57,"ref":0.00004682},{"open":1.2e-7,"high":1.2e-7,"low":1.2e-7,"close":1.2e-7,"time":1681535436306,"volume":212.45,"ref":0.00004683},{"open":1.2e-7,"high":1.5e-7,"low":1.2e-7,"close":1.5e-7,"time":1681535496320,"volume":476.1700000000001,"ref":0.00004683},{"open":1.5e-7,"high":1.5e-7,"low":1.4e-7,"close":1.4e-7,"time":1681535556527,"volume":324.06,"ref":0.00004683},{"open":1.4e-7,"high":1.7e-7,"low":9e-8,"close":1.4e-7,"time":1681535692872,"volume":1342.16,"ref":0.00004682},{"open":1.4e-7,"high":1.4e-7,"low":1.3e-7,"close":1.3e-7,"time":1681535754597,"volume":292.65999999999997,"ref":0.00004684},{"open":1.3e-7,"high":1.3e-7,"low":1.3e-7,"close":1.3e-7,"time":1681535814362,"volume":0,"ref":0.00004684},{"open":1.3e-7,"high":1.5e-7,"low":8e-8,"close":1e-7,"time":1681535874797,"volume":744.5600000000001,"ref":0.00004682},{"open":1e-7,"high":1e-7,"low":1e-7,"close":1e-7,"time":1681535934554,"volume":73.16,"ref":0.00004682},{"open":1e-7,"high":1.6e-7,"low":1e-7,"close":1.5e-7,"time":1681535994782,"volume":313.93,"ref":0.00004682},{"open":1.5e-7,"high":1.5e-7,"low":1.4e-7,"close":1.4e-7,"time":1681536055555,"volume":91.61,"ref":0.00004683},{"open":1.4e-7,"high":1.4e-7,"low":1.2e-7,"close":1.2e-7,"time":1681536114550,"volume":298.13,"ref":0.00004686},{"open":1.2e-7,"high":1.2e-7,"low":1.2e-7,"close":1.2e-7,"time":1681536175039,"volume":0,"ref":0.00004686},{"open":1.2e-7,"high":1.3e-7,"low":1.2e-7,"close":1.2e-7,"time":1681536235033,"volume":776.49,"ref":0.00004686},{"open":1.2e-7,"high":1.3e-7,"low":1.2e-7,"close":1.2e-7,"time":1681536294774,"volume":305.94,"ref":0.00004686},{"open":1.2e-7,"high":1.3e-7,"low":1.2e-7,"close":1.2e-7,"time":1681536355021,"volume":182.1,"ref":0.00004686},{"open":1.2e-7,"high":1.2e-7,"low":1.2e-7,"close":1.2e-7,"time":1681536414780,"volume":0,"ref":0.00004686},{"open":1.2e-7,"high":1.2e-7,"low":7e-8,"close":7e-8,"time":1681536475017,"volume":493.07000000000005,"ref":0.00004693},{"open":7e-8,"high":2.1e-7,"low":6e-8,"close":2e-7,"time":1681536534785,"volume":1034.25,"ref":0.00004691},{"open":2e-7,"high":2e-7,"low":4e-8,"close":8e-8,"time":1681536595246,"volume":1849.6200000000001,"ref":0.00004705},{"open":8e-8,"high":1.2e-7,"low":8e-8,"close":8e-8,"time":1681536654998,"volume":900.26,"ref":0.00004705},{"open":8e-8,"high":1.6e-7,"low":7e-8,"close":1e-7,"time":1681536715241,"volume":1169.16,"ref":0.00004706},{"open":1e-7,"high":1.1e-7,"low":1e-7,"close":1e-7,"time":1681536775504,"volume":151.4,"ref":0.00004704},{"open":1e-7,"high":1e-7,"low":9e-8,"close":9e-8,"time":1681536835030,"volume":87,"ref":0.00004705},{"open":9e-8,"high":9e-8,"low":7e-8,"close":7e-8,"time":1681536895257,"volume":1489.7800000000002,"ref":0.00004707},{"open":7e-8,"high":7e-8,"low":7e-8,"close":7e-8,"time":1681536955275,"volume":21.11,"ref":0.00004707},{"open":7e-8,"high":1.3e-7,"low":7e-8,"close":1.3e-7,"time":1681537015027,"volume":774.01,"ref":0.00004707},{"open":1.3e-7,"high":1.3e-7,"low":1.1e-7,"close":1.1e-7,"time":1681537075598,"volume":276.71,"ref":0.00004707},{"open":1.1e-7,"high":1.2e-7,"low":9e-8,"close":9e-8,"time":1681537135834,"volume":657.38,"ref":0.00004706},{"open":9e-8,"high":1.1e-7,"low":9e-8,"close":1e-7,"time":1681537195344,"volume":1146.1699999999998,"ref":0.00004707},{"open":1e-7,"high":1.3e-7,"low":8e-8,"close":9e-8,"time":1681537255362,"volume":909.3299999999999,"ref":0.00004709},{"open":9e-8,"high":1.2e-7,"low":7e-8,"close":7e-8,"time":1681537314255,"volume":433.09,"ref":0.00004713},{"open":7e-8,"high":1.2e-7,"low":7e-8,"close":1.2e-7,"time":1681537375509,"volume":524.72,"ref":0.00004708},{"open":1.2e-7,"high":1.2e-7,"low":9e-8,"close":1.1e-7,"time":1681537436022,"volume":335.84999999999997,"ref":0.00004709},{"open":1.1e-7,"high":1.1e-7,"low":7e-8,"close":9e-8,"time":1681537495516,"volume":1715.5700000000002,"ref":0.00004711},{"open":9e-8,"high":9e-8,"low":6e-8,"close":8e-8,"time":1681537555761,"volume":2649.2100000000005,"ref":0.00004712},{"open":8e-8,"high":8e-8,"low":8e-8,"close":8e-8,"time":1681537615524,"volume":0,"ref":0.00004712},{"open":8e-8,"high":8e-8,"low":8e-8,"close":8e-8,"time":1681537673587,"volume":322.56,"ref":0.00004711},{"open":8e-8,"high":1.2e-7,"low":8e-8,"close":1e-7,"time":1681537736070,"volume":1094.99,"ref":0.00004709},{"open":1e-7,"high":1e-7,"low":9e-8,"close":9e-8,"time":1681537796091,"volume":73.45,"ref":0.0000471},{"open":9e-8,"high":1.6e-7,"low":9e-8,"close":1.6e-7,"time":1681537856825,"volume":512.96,"ref":0.0000469},{"open":1.6e-7,"high":1.6e-7,"low":7e-8,"close":7e-8,"time":1681537916079,"volume":704.8799999999999,"ref":0.0000469},{"open":7e-8,"high":8e-8,"low":7e-8,"close":8e-8,"time":1681537975826,"volume":176.78,"ref":0.0000469},{"open":8e-8,"high":8e-8,"low":6e-8,"close":7e-8,"time":1681538036584,"volume":741.97,"ref":0.0000469},{"open":7e-8,"high":2.8e-7,"low":7e-8,"close":9e-8,"time":1681538096573,"volume":470.67,"ref":0.00004687},{"open":9e-8,"high":9e-8,"low":5e-8,"close":5e-8,"time":1681538156339,"volume":79.19,"ref":0.00004687},{"open":5e-8,"high":5e-8,"low":5e-8,"close":5e-8,"time":1681538216315,"volume":59.44,"ref":0.00004687},{"open":5e-8,"high":7e-8,"low":4e-8,"close":7e-8,"time":1681538276325,"volume":244.60999999999999,"ref":0.00004686},{"open":7e-8,"high":7e-8,"low":7e-8,"close":7e-8,"time":1681538336335,"volume":0,"ref":0.00004686},{"open":7e-8,"high":7e-8,"low":7e-8,"close":7e-8,"time":1681538395801,"volume":138.26,"ref":0.00004686},{"open":7e-8,"high":1.6e-7,"low":7e-8,"close":1.5e-7,"time":1681538456554,"volume":1004.8900000000001,"ref":0.00004687},{"open":1.5e-7,"high":1.9e-7,"low":1.3e-7,"close":1.4e-7,"time":1681538516543,"volume":1460.4699999999998,"ref":0.00004696},{"open":1.4e-7,"high":1.4e-7,"low":1.1e-7,"close":1.1e-7,"time":1681538576762,"volume":256.61,"ref":0.00004699},{"open":1.1e-7,"high":1.1e-7,"low":1.1e-7,"close":1.1e-7,"time":1681538637028,"volume":650.3900000000001,"ref":0.00004699},{"open":1.1e-7,"high":1.5e-7,"low":8e-8,"close":1.1e-7,"time":1681538696765,"volume":1582.3600000000001,"ref":0.00004687},{"open":1.1e-7,"high":1.8e-7,"low":1.1e-7,"close":1.3e-7,"time":1681538756784,"volume":411.9,"ref":0.00004694},{"open":1.3e-7,"high":1.8e-7,"low":1.1e-7,"close":1.1e-7,"time":1681538816773,"volume":1380.4900000000002,"ref":0.0000469},{"open":1.1e-7,"high":2e-7,"low":1.1e-7,"close":1.7e-7,"time":1681538877241,"volume":674.01,"ref":0.0000469},{"open":1.7e-7,"high":1.7e-7,"low":1.6e-7,"close":1.6e-7,"time":1681538939250,"volume":644.64,"ref":0.0000469},{"open":1.6e-7,"high":2e-7,"low":1.2e-7,"close":1.2e-7,"time":1681538999990,"volume":995.0699999999999,"ref":0.00004697},{"open":1.2e-7,"high":1.4e-7,"low":8e-8,"close":1.1e-7,"time":1681539057450,"volume":1710.72,"ref":0.00004699},{"open":1.1e-7,"high":1.1e-7,"low":9e-8,"close":9e-8,"time":1681539117460,"volume":1925.1100000000001,"ref":0.00004699},{"open":9e-8,"high":1.5e-7,"low":9e-8,"close":1.4e-7,"time":1681539177195,"volume":433.83000000000004,"ref":0.00004695},{"open":1.4e-7,"high":1.4e-7,"low":1.3e-7,"close":1.3e-7,"time":1681539308198,"volume":165.34,"ref":0.00004695},{"open":1.3e-7,"high":1.3e-7,"low":1e-8,"close":2e-8,"time":1681539369871,"volume":1088.1399999999999,"ref":0.00004686},{"open":2e-8,"high":9e-8,"low":2e-8,"close":9e-8,"time":1681539429388,"volume":441.85,"ref":0.00004682},{"open":9e-8,"high":2.1e-7,"low":9e-8,"close":1.2e-7,"time":1681539489377,"volume":1180.5800000000002,"ref":0.00004682},{"open":1.2e-7,"high":1.2e-7,"low":1.2e-7,"close":1.2e-7,"time":1681539549634,"volume":0,"ref":0.00004682},{"open":1.2e-7,"high":1.8e-7,"low":1.2e-7,"close":1.3e-7,"time":1681539610103,"volume":856.34,"ref":0.0000469},{"open":1.3e-7,"high":1.3e-7,"low":1.3e-7,"close":1.3e-7,"time":1681539669617,"volume":475.09000000000003,"ref":0.0000469},{"open":1.3e-7,"high":2.2e-7,"low":1.3e-7,"close":1.4e-7,"time":1681539729610,"volume":1266.9199999999998,"ref":0.00004686},{"open":1.4e-7,"high":1.6e-7,"low":1.3e-7,"close":1.3e-7,"time":1681539789605,"volume":474.4800000000001,"ref":0.00004681},{"open":1.3e-7,"high":1.3e-7,"low":1.1e-7,"close":1.1e-7,"time":1681539849614,"volume":71.3,"ref":0.00004683},{"open":1.1e-7,"high":1.1e-7,"low":1.1e-7,"close":1.1e-7,"time":1681539910255,"volume":0,"ref":0.00004683},{"open":1.1e-7,"high":1.1e-7,"low":1.1e-7,"close":1.1e-7,"time":1681539969753,"volume":0,"ref":0.00004683},{"open":1.1e-7,"high":1.1e-7,"low":1e-7,"close":1.1e-7,"time":1681540029994,"volume":205.83999999999997,"ref":0.00004683},{"open":1.1e-7,"high":1.1e-7,"low":1e-7,"close":1e-7,"time":1681540089760,"volume":4.53,"ref":0.00004683},{"open":1e-7,"high":1.1e-7,"low":1e-7,"close":1.1e-7,"time":1681540149747,"volume":71.3,"ref":0.00004683},{"open":1.1e-7,"high":1.1e-7,"low":1.1e-7,"close":1.1e-7,"time":1681540208716,"volume":210.77,"ref":0.00004683},{"open":1.1e-7,"high":1.8e-7,"low":1.1e-7,"close":1.6e-7,"time":1681540269971,"volume":1673.6,"ref":0.00004684},{"open":1.6e-7,"high":1.7e-7,"low":1.5e-7,"close":1.6e-7,"time":1681540329970,"volume":634.38,"ref":0.00004683},{"open":1.6e-7,"high":1.9e-7,"low":1e-7,"close":1.4e-7,"time":1681540390890,"volume":722.99,"ref":0.00004683},{"open":1.4e-7,"high":2.1e-7,"low":1.4e-7,"close":1.9e-7,"time":1681540450385,"volume":402.21,"ref":0.00004683},{"open":1.9e-7,"high":1.9e-7,"low":1.6e-7,"close":1.7e-7,"time":1681540507604,"volume":547.75,"ref":0.00004685},{"open":1.7e-7,"high":1.9e-7,"low":1.6e-7,"close":1.6e-7,"time":1681540573623,"volume":867.0899999999999,"ref":0.00004685},{"open":1.6e-7,"high":1.6e-7,"low":1.4e-7,"close":1.4e-7,"time":1681540630363,"volume":344,"ref":0.00004685},{"open":1.4e-7,"high":1.5e-7,"low":1.3e-7,"close":1.3e-7,"time":1681540690600,"volume":382.78999999999996,"ref":0.00004684},{"open":1.3e-7,"high":1.6e-7,"low":1e-7,"close":1.3e-7,"time":1681540751018,"volume":914.8500000000001,"ref":0.00004684},{"open":1.3e-7,"high":1.6e-7,"low":1.2e-7,"close":1.4e-7,"time":1681540811043,"volume":1062.29,"ref":0.00004684},{"open":1.4e-7,"high":1.4e-7,"low":1.3e-7,"close":1.3e-7,"time":1681540870788,"volume":97.44,"ref":0.00004684},{"open":1.3e-7,"high":1.9e-7,"low":1.3e-7,"close":1.7e-7,"time":1681540928731,"volume":740.33,"ref":0.00004686},{"open":1.7e-7,"high":1.7e-7,"low":1.5e-7,"close":1.5e-7,"time":1681540991501,"volume":1000.5100000000001,"ref":0.00004688},{"open":1.5e-7,"high":1.5e-7,"low":1.5e-7,"close":1.5e-7,"time":1681541051010,"volume":0,"ref":0.00004688},{"open":1.5e-7,"high":1.5e-7,"low":1.4e-7,"close":1.5e-7,"time":1681541111234,"volume":106.56,"ref":0.00004688},{"open":1.5e-7,"high":1.5e-7,"low":1.5e-7,"close":1.5e-7,"time":1681541171237,"volume":0,"ref":0.00004688},{"open":1.5e-7,"high":2e-7,"low":1.5e-7,"close":1.5e-7,"time":1681541231486,"volume":113.96000000000001,"ref":0.00004689},{"open":1.5e-7,"high":1.8e-7,"low":1.4e-7,"close":1.6e-7,"time":1681541291497,"volume":1583.35,"ref":0.00004685},{"open":1.6e-7,"high":1.7e-7,"low":1.6e-7,"close":1.6e-7,"time":1681541350995,"volume":242.9,"ref":0.00004684},{"open":1.6e-7,"high":1.6e-7,"low":1.4e-7,"close":1.5e-7,"time":1681541411469,"volume":521.69,"ref":0.00004683},{"open":1.5e-7,"high":2.1e-7,"low":1.4e-7,"close":1.4e-7,"time":1681541471480,"volume":983.26,"ref":0.00004684},{"open":1.4e-7,"high":1.8e-7,"low":1.4e-7,"close":1.5e-7,"time":1681541531514,"volume":1473.4400000000003,"ref":0.00004686},{"open":1.5e-7,"high":1.7e-7,"low":1.5e-7,"close":1.7e-7,"time":1681541591506,"volume":14.63,"ref":0.00004684},{"open":1.7e-7,"high":2.1e-7,"low":1.7e-7,"close":1.8e-7,"time":1681541651501,"volume":413.88,"ref":0.00004684},{"open":1.8e-7,"high":1.8e-7,"low":1.6e-7,"close":1.8e-7,"time":1681541711264,"volume":351.5,"ref":0.00004686},{"open":1.8e-7,"high":1.8e-7,"low":1.6e-7,"close":1.6e-7,"time":1681541771256,"volume":1310.61,"ref":0.00004688},{"open":1.6e-7,"high":1.7e-7,"low":1.3e-7,"close":1.6e-7,"time":1681541830037,"volume":774.5700000000002,"ref":0.00004684},{"open":1.6e-7,"high":2.2e-7,"low":1.6e-7,"close":1.9e-7,"time":1681541891774,"volume":695.75,"ref":0.00004684},{"open":1.9e-7,"high":2.3e-7,"low":1.4e-7,"close":1.5e-7,"time":1681541951536,"volume":1518.5100000000002,"ref":0.00004684},{"open":1.5e-7,"high":1.7e-7,"low":1.5e-7,"close":1.7e-7,"time":1681542011769,"volume":63.42,"ref":0.00004684},{"open":1.7e-7,"high":2.2e-7,"low":1.3e-7,"close":1.4e-7,"time":1681542071768,"volume":1719.28,"ref":0.00004692},{"open":1.4e-7,"high":1.6e-7,"low":1.2e-7,"close":1.5e-7,"time":1681542132007,"volume":1383.2400000000002,"ref":0.00004691},{"open":1.5e-7,"high":1.5e-7,"low":1.5e-7,"close":1.5e-7,"time":1681542191747,"volume":0,"ref":0.00004691},{"open":1.5e-7,"high":2e-7,"low":1.5e-7,"close":1.9e-7,"time":1681542251763,"volume":53.04,"ref":0.00004687},{"open":1.9e-7,"high":1.9e-7,"low":1.4e-7,"close":1.4e-7,"time":1681542311753,"volume":263.76,"ref":0.0000469},{"open":1.4e-7,"high":1.7e-7,"low":1.4e-7,"close":1.6e-7,"time":1681542370007,"volume":246.16,"ref":0.00004689},{"open":1.6e-7,"high":1.6e-7,"low":1.3e-7,"close":1.4e-7,"time":1681542431991,"volume":103.39,"ref":0.00004692},{"open":1.4e-7,"high":1.6e-7,"low":1.3e-7,"close":1.6e-7,"time":1681542491753,"volume":67.14,"ref":0.00004689},{"open":1.6e-7,"high":1.6e-7,"low":1.6e-7,"close":1.6e-7,"time":1681542551759,"volume":0,"ref":0.00004689},{"open":1.6e-7,"high":1.6e-7,"low":1.5e-7,"close":1.5e-7,"time":1681542611993,"volume":52.3,"ref":0.0000469},{"open":1.5e-7,"high":1.5e-7,"low":1.5e-7,"close":1.5e-7,"time":1681542669800,"volume":0,"ref":0.0000469},{"open":1.5e-7,"high":1.5e-7,"low":1.4e-7,"close":1.5e-7,"time":1681542732055,"volume":97.24,"ref":0.00004691},{"open":1.5e-7,"high":1.5e-7,"low":1.5e-7,"close":1.5e-7,"time":1681542791801,"volume":0,"ref":0.00004691},{"open":1.5e-7,"high":1.5e-7,"low":1.5e-7,"close":1.5e-7,"time":1681543026783,"volume":49.52,"ref":0.00004691},{"open":1.5e-7,"high":1.5e-7,"low":1.5e-7,"close":1.5e-7,"time":1681543075787,"volume":50.48,"ref":0.00004691},{"open":1.5e-7,"high":2.1e-7,"low":1.5e-7,"close":2e-7,"time":1681543132793,"volume":412.72,"ref":0.00004689},{"open":2e-7,"high":2e-7,"low":1.4e-7,"close":1.4e-7,"time":1681543188297,"volume":358.72,"ref":0.00004691},{"open":1.4e-7,"high":1.6e-7,"low":1e-7,"close":1e-7,"time":1681543248304,"volume":866.5800000000002,"ref":0.00004698},{"open":1e-7,"high":1.4e-7,"low":7e-8,"close":7e-8,"time":1681543308554,"volume":198.23,"ref":0.00004701},{"open":7e-8,"high":1.3e-7,"low":6e-8,"close":6e-8,"time":1681543368715,"volume":251.76999999999998,"ref":0.00004702},{"open":6e-8,"high":1.3e-7,"low":6e-8,"close":1.3e-7,"time":1681543428472,"volume":86.25999999999999,"ref":0.00004695},{"open":1.3e-7,"high":1.3e-7,"low":6e-8,"close":6e-8,"time":1681543488468,"volume":50.88,"ref":0.00004702},{"open":6e-8,"high":1.3e-7,"low":6e-8,"close":8e-8,"time":1681543548728,"volume":139.7,"ref":0.000047},{"open":8e-8,"high":1.3e-7,"low":7e-8,"close":1e-7,"time":1681543608477,"volume":234.82000000000002,"ref":0.00004698},{"open":1e-7,"high":1.7e-7,"low":9e-8,"close":1e-7,"time":1681543668715,"volume":340.65999999999997,"ref":0.00004698},{"open":1e-7,"high":1e-7,"low":1e-7,"close":1e-7,"time":1681543728702,"volume":0,"ref":0.00004698},{"open":1e-7,"high":1.2e-7,"low":1e-7,"close":1.1e-7,"time":1681543788717,"volume":218.89000000000001,"ref":0.00004698},{"open":1.1e-7,"high":1.1e-7,"low":1.1e-7,"close":1.1e-7,"time":1681543849450,"volume":0,"ref":0.00004698},{"open":1.1e-7,"high":1.1e-7,"low":1.1e-7,"close":1.1e-7,"time":1681543908935,"volume":0,"ref":0.00004698},{"open":1.1e-7,"high":1.6e-7,"low":1.1e-7,"close":1.6e-7,"time":1681543968931,"volume":36.63,"ref":0.00004693},{"open":1.6e-7,"high":1.6e-7,"low":1.5e-7,"close":1.5e-7,"time":1681544028942,"volume":36.61,"ref":0.00004694},{"open":1.5e-7,"high":1.9e-7,"low":1.3e-7,"close":1.3e-7,"time":1681544089633,"volume":560.0799999999999,"ref":0.00004696},{"open":1.3e-7,"high":1.6e-7,"low":1.3e-7,"close":1.5e-7,"time":1681544149641,"volume":529.79,"ref":0.00004694},{"open":1.5e-7,"high":1.5e-7,"low":1.5e-7,"close":1.5e-7,"time":1681544209384,"volume":0,"ref":0.00004694},{"open":1.5e-7,"high":1.5e-7,"low":1.5e-7,"close":1.5e-7,"time":1681544269385,"volume":0,"ref":0.00004694},{"open":1.5e-7,"high":1.5e-7,"low":1.4e-7,"close":1.5e-7,"time":1681544329151,"volume":1085.12,"ref":0.00004694},{"open":1.5e-7,"high":1.5e-7,"low":1.3e-7,"close":1.3e-7,"time":1681544389899,"volume":54.07,"ref":0.00004696},{"open":1.3e-7,"high":1.3e-7,"low":1.3e-7,"close":1.3e-7,"time":1681544449393,"volume":0,"ref":0.00004696},{"open":1.3e-7,"high":1.3e-7,"low":1.3e-7,"close":1.3e-7,"time":1681544509391,"volume":0,"ref":0.00004696},{"open":1.3e-7,"high":1.3e-7,"low":1.2e-7,"close":1.2e-7,"time":1681544569393,"volume":650.3,"ref":0.00004694},{"open":1.2e-7,"high":1.2e-7,"low":1.2e-7,"close":1.2e-7,"time":1681544630130,"volume":0,"ref":0.00004694},{"open":1.2e-7,"high":1.5e-7,"low":1e-7,"close":1e-7,"time":1681544689623,"volume":1250.72,"ref":0.00004694},{"open":1e-7,"high":1e-7,"low":8e-8,"close":8e-8,"time":1681544749631,"volume":1834.44,"ref":0.00004691},{"open":8e-8,"high":1.9e-7,"low":6e-8,"close":8e-8,"time":1681544809631,"volume":4317.56,"ref":0.00004685},{"open":8e-8,"high":2.1e-7,"low":3e-8,"close":3e-8,"time":1681544869793,"volume":9124.33,"ref":0.00004685},{"open":3e-8,"high":2e-7,"low":3e-8,"close":2e-7,"time":1681544929534,"volume":1830.9499999999998,"ref":0.00004685},{"open":2e-7,"high":2.2e-7,"low":5e-8,"close":5e-8,"time":1681544989551,"volume":2375.1800000000003,"ref":0.00004683},{"open":5e-8,"high":2.2e-7,"low":5e-8,"close":1e-7,"time":1681545049779,"volume":1844.66,"ref":0.00004683},{"open":1e-7,"high":1.2e-7,"low":9e-8,"close":1.1e-7,"time":1681545109775,"volume":1236.16,"ref":0.00004683},{"open":1.1e-7,"high":1.1e-7,"low":8e-8,"close":8e-8,"time":1681545170378,"volume":3901.6400000000017,"ref":0.00004683},{"open":8e-8,"high":8e-8,"low":5e-8,"close":8e-8,"time":1681545230129,"volume":3795.930000000001,"ref":0.00004683},{"open":8e-8,"high":8e-8,"low":6e-8,"close":6e-8,"time":1681545289653,"volume":4813.330000000001,"ref":0.00004683},{"open":6e-8,"high":2.5e-7,"low":2e-8,"close":3e-8,"time":1681545350136,"volume":3575.349999999999,"ref":0.0000468},{"open":3e-8,"high":3e-8,"low":3e-8,"close":3e-8,"time":1681545410203,"volume":2147.9,"ref":0.0000468},{"open":3e-8,"high":3e-8,"low":3e-8,"close":3e-8,"time":1681545469951,"volume":3866.22,"ref":0.0000468},{"open":3e-8,"high":3e-8,"low":3e-8,"close":3e-8,"time":1681545529950,"volume":1718.32,"ref":0.0000468},{"open":3e-8,"high":1.6e-7,"low":3e-8,"close":1.1e-7,"time":1681545590626,"volume":940.4300000000001,"ref":0.00004681},{"open":1.1e-7,"high":1.6e-7,"low":1.1e-7,"close":1.6e-7,"time":1681545650380,"volume":718.94,"ref":0.00004681},{"open":1.6e-7,"high":1.6e-7,"low":1.6e-7,"close":1.6e-7,"time":1681545710375,"volume":0,"ref":0.00004681},{"open":1.6e-7,"high":1.6e-7,"low":1.4e-7,"close":1.4e-7,"time":1681545770830,"volume":583.5,"ref":0.0000468},{"open":1.4e-7,"high":1.4e-7,"low":1.4e-7,"close":1.4e-7,"time":1681545830603,"volume":0,"ref":0.0000468},{"open":1.4e-7,"high":1.4e-7,"low":1.4e-7,"close":1.4e-7,"time":1681545890577,"volume":126.49,"ref":0.00004681},{"open":1.4e-7,"high":2.6e-7,"low":1.4e-7,"close":1.7e-7,"time":1681545951163,"volume":430.61,"ref":0.00004681},{"open":1.7e-7,"high":1.7e-7,"low":1.7e-7,"close":1.7e-7,"time":1681546010655,"volume":0,"ref":0.00004681},{"open":1.7e-7,"high":1.7e-7,"low":1.6e-7,"close":1.6e-7,"time":1681546070674,"volume":123.59,"ref":0.00004681},{"open":1.6e-7,"high":2.7e-7,"low":1.6e-7,"close":2.7e-7,"time":1681546130914,"volume":1571.8299999999997,"ref":0.00004681},{"open":2.7e-7,"high":2.7e-7,"low":1.5e-7,"close":1.5e-7,"time":1681546191572,"volume":3307.9700000000003,"ref":0.00004681},{"open":1.5e-7,"high":1.5e-7,"low":1e-7,"close":1e-7,"time":1681546251075,"volume":485.56,"ref":0.00004681},{"open":1e-7,"high":1e-7,"low":1e-7,"close":1e-7,"time":1681546311570,"volume":0,"ref":0.00004681},{"open":1e-7,"high":1e-7,"low":1e-7,"close":1e-7,"time":1681546371072,"volume":0,"ref":0.00004681},{"open":1e-7,"high":1.6e-7,"low":9e-8,"close":9e-8,"time":1681546540843,"volume":297.06,"ref":0.00004679},{"open":9e-8,"high":1.2e-7,"low":9e-8,"close":1.1e-7,"time":1681546602294,"volume":98.41,"ref":0.00004679},{"open":1.1e-7,"high":1.1e-7,"low":1.1e-7,"close":1.1e-7,"time":1681546662273,"volume":0,"ref":0.00004679},{"open":1.1e-7,"high":1.1e-7,"low":1.1e-7,"close":1.1e-7,"time":1681546722020,"volume":150.29,"ref":0.00004679},{"open":1.1e-7,"high":1.1e-7,"low":1.1e-7,"close":1.1e-7,"time":1681546782272,"volume":100.36,"ref":0.00004679},{"open":1.1e-7,"high":1.1e-7,"low":1e-7,"close":1.1e-7,"time":1681546842740,"volume":260.38,"ref":0.00004679},{"open":1.1e-7,"high":1.1e-7,"low":9e-8,"close":9e-8,"time":1681546902242,"volume":328.71,"ref":0.00004679},{"open":9e-8,"high":1.8e-7,"low":5e-8,"close":1.5e-7,"time":1681546962237,"volume":1178.5300000000002,"ref":0.00004684},{"open":1.5e-7,"high":1.5e-7,"low":1.4e-7,"close":1.4e-7,"time":1681547022641,"volume":384.77,"ref":0.00004684},{"open":1.4e-7,"high":1.4e-7,"low":1.4e-7,"close":1.4e-7,"time":1681547086141,"volume":0,"ref":0.00004684},{"open":1.4e-7,"high":1.4e-7,"low":1.3e-7,"close":1.3e-7,"time":1681547142885,"volume":191.53,"ref":0.00004685},{"open":1.3e-7,"high":1.3e-7,"low":1.3e-7,"close":1.3e-7,"time":1681547202641,"volume":0,"ref":0.00004685},{"open":1.3e-7,"high":1.4e-7,"low":1.3e-7,"close":1.3e-7,"time":1681547262655,"volume":1212.84,"ref":0.00004685},{"open":1.3e-7,"high":1.4e-7,"low":1.3e-7,"close":1.3e-7,"time":1681547323564,"volume":401.49,"ref":0.00004685},{"open":1.3e-7,"high":1.3e-7,"low":1.1e-7,"close":1.1e-7,"time":1681547383074,"volume":628.99,"ref":0.00004686},{"open":1.1e-7,"high":1.1e-7,"low":1.1e-7,"close":1.1e-7,"time":1681547442831,"volume":0,"ref":0.00004686},{"open":1.1e-7,"high":1.3e-7,"low":1.1e-7,"close":1.3e-7,"time":1681547503064,"volume":184.8,"ref":0.00004684},{"open":1.3e-7,"high":1.3e-7,"low":1.3e-7,"close":1.3e-7,"time":1681547563547,"volume":341.84000000000003,"ref":0.00004685},{"open":1.3e-7,"high":1.3e-7,"low":1.3e-7,"close":1.3e-7,"time":1681547623052,"volume":0,"ref":0.00004685},{"open":1.3e-7,"high":1.5e-7,"low":1.3e-7,"close":1.5e-7,"time":1681547683287,"volume":164.37,"ref":0.00004685},{"open":1.5e-7,"high":1.5e-7,"low":4e-8,"close":1.2e-7,"time":1681547743783,"volume":515,"ref":0.00004684},{"open":1.2e-7,"high":1.5e-7,"low":1.2e-7,"close":1.5e-7,"time":1681547803879,"volume":231.9,"ref":0.00004685},{"open":1.5e-7,"high":1.5e-7,"low":1.5e-7,"close":1.5e-7,"time":1681547863379,"volume":0,"ref":0.00004685},{"open":1.5e-7,"high":1.5e-7,"low":1.5e-7,"close":1.5e-7,"time":1681547923369,"volume":0,"ref":0.00004685},{"open":1.5e-7,"high":1.5e-7,"low":1.5e-7,"close":1.5e-7,"time":1681547983377,"volume":280.14,"ref":0.00004685},{"open":1.5e-7,"high":1.5e-7,"low":1e-7,"close":1e-7,"time":1681548043715,"volume":518.66,"ref":0.0000469},{"open":1e-7,"high":1e-7,"low":6e-8,"close":6e-8,"time":1681548103459,"volume":690.68,"ref":0.00004694},{"open":6e-8,"high":8e-8,"low":2e-8,"close":6e-8,"time":1681548164173,"volume":619.35,"ref":0.00004694},{"open":6e-8,"high":6e-8,"low":6e-8,"close":6e-8,"time":1681548223906,"volume":0,"ref":0.00004694},{"open":6e-8,"high":1.2e-7,"low":6e-8,"close":1.2e-7,"time":1681548283676,"volume":121.63,"ref":0.00004695},{"open":1.2e-7,"high":1.2e-7,"low":1.1e-7,"close":1.1e-7,"time":1681548343924,"volume":142.82,"ref":0.00004694},{"open":1.1e-7,"high":1.1e-7,"low":1.1e-7,"close":1.1e-7,"time":1681548404406,"volume":0,"ref":0.00004694},{"open":1.1e-7,"high":1.1e-7,"low":1.1e-7,"close":1.1e-7,"time":1681548464140,"volume":142.82,"ref":0.00004694},{"open":1.1e-7,"high":1.3e-7,"low":1e-7,"close":1e-7,"time":1681548523901,"volume":1801.83,"ref":0.00004694},{"open":1e-7,"high":1.2e-7,"low":6e-8,"close":1.1e-7,"time":1681548584145,"volume":2730.61,"ref":0.00004692},{"open":1.1e-7,"high":1.6e-7,"low":5e-8,"close":1.4e-7,"time":1681548644423,"volume":3753.64,"ref":0.00004692},{"open":1.4e-7,"high":1.4e-7,"low":1.4e-7,"close":1.4e-7,"time":1681548704164,"volume":4464.09,"ref":0.00004691},{"open":1.4e-7,"high":1.4e-7,"low":8e-8,"close":1.2e-7,"time":1681548763927,"volume":4722.93,"ref":0.00004696},{"open":1.2e-7,"high":1.2e-7,"low":1.2e-7,"close":1.2e-7,"time":1681548824150,"volume":0,"ref":0.00004696},{"open":1.2e-7,"high":1.2e-7,"low":1.2e-7,"close":1.2e-7,"time":1681548884414,"volume":0,"ref":0.00004696},{"open":1.2e-7,"high":1.2e-7,"low":1.2e-7,"close":1.2e-7,"time":1681548944158,"volume":0,"ref":0.00004696},{"open":1.2e-7,"high":1.5e-7,"low":1.2e-7,"close":1.5e-7,"time":1681549004150,"volume":87.73,"ref":0.00004693},{"open":1.5e-7,"high":1.5e-7,"low":1.2e-7,"close":1.2e-7,"time":1681549064164,"volume":810.74,"ref":0.00004694},{"open":1.2e-7,"high":1.2e-7,"low":1.2e-7,"close":1.2e-7,"time":1681549124153,"volume":0,"ref":0.00004694},{"open":1.2e-7,"high":1.6e-7,"low":1.2e-7,"close":1.3e-7,"time":1681549184738,"volume":1812.15,"ref":0.00004693},{"open":1.3e-7,"high":1.5e-7,"low":1.3e-7,"close":1.5e-7,"time":1681549244248,"volume":936.7700000000001,"ref":0.00004693},{"open":1.5e-7,"high":1.5e-7,"low":1.5e-7,"close":1.5e-7,"time":1681549304233,"volume":110.78,"ref":0.00004693},{"open":1.5e-7,"high":1.5e-7,"low":1.5e-7,"close":1.5e-7,"time":1681549365211,"volume":256.12,"ref":0.00004693},{"open":1.5e-7,"high":1.5e-7,"low":1.5e-7,"close":1.5e-7,"time":1681549424463,"volume":0,"ref":0.00004693},{"open":1.5e-7,"high":1.5e-7,"low":1.4e-7,"close":1.4e-7,"time":1681549484460,"volume":534.7,"ref":0.00004693},{"open":1.4e-7,"high":1.4e-7,"low":1.4e-7,"close":1.4e-7,"time":1681549544721,"volume":0,"ref":0.00004693},{"open":1.4e-7,"high":1.4e-7,"low":1.4e-7,"close":1.4e-7,"time":1681549605193,"volume":0,"ref":0.00004693},{"open":1.4e-7,"high":1.4e-7,"low":1.4e-7,"close":1.4e-7,"time":1681549664935,"volume":1570.1799999999998,"ref":0.00004693},{"open":1.4e-7,"high":1.4e-7,"low":1.4e-7,"close":1.4e-7,"time":1681549724427,"volume":0,"ref":0.00004693},{"open":1.4e-7,"high":1.9e-7,"low":1e-7,"close":1.1e-7,"time":1681549784675,"volume":1199.5400000000002,"ref":0.00004694},{"open":1.1e-7,"high":1.6e-7,"low":1.1e-7,"close":1.6e-7,"time":1681549846245,"volume":1549.73,"ref":0.00004689},{"open":1.6e-7,"high":1.7e-7,"low":1.2e-7,"close":1.2e-7,"time":1681549904985,"volume":1209.09,"ref":0.00004692},{"open":1.2e-7,"high":1.4e-7,"low":1.2e-7,"close":1.4e-7,"time":1681549964977,"volume":23.55,"ref":0.00004692},{"open":1.4e-7,"high":1.4e-7,"low":1.3e-7,"close":1.4e-7,"time":1681550159087,"volume":263.29,"ref":0.00004692},{"open":1.4e-7,"high":1.4e-7,"low":1.4e-7,"close":1.4e-7,"time":1681550221335,"volume":365.06,"ref":0.00004691},{"open":1.4e-7,"high":1.4e-7,"low":1.4e-7,"close":1.4e-7,"time":1681550281080,"volume":0,"ref":0.00004691},{"open":1.4e-7,"high":1.8e-7,"low":1.4e-7,"close":1.8e-7,"time":1681550340579,"volume":430.06,"ref":0.00004687},{"open":1.8e-7,"high":1.8e-7,"low":1.6e-7,"close":1.6e-7,"time":1681550400840,"volume":143.9,"ref":0.00004689},{"open":1.6e-7,"high":1.6e-7,"low":1.6e-7,"close":1.6e-7,"time":1681550461329,"volume":0,"ref":0.00004689},{"open":1.6e-7,"high":1.7e-7,"low":1.6e-7,"close":1.7e-7,"time":1681550521054,"volume":147.93,"ref":0.00004688},{"open":1.7e-7,"high":1.7e-7,"low":1.6e-7,"close":1.6e-7,"time":1681550580812,"volume":147.25,"ref":0.00004689},{"open":1.6e-7,"high":1.6e-7,"low":1.6e-7,"close":1.6e-7,"time":1681550641028,"volume":0,"ref":0.00004689},{"open":1.6e-7,"high":1.6e-7,"low":1.5e-7,"close":1.5e-7,"time":1681550701285,"volume":143.9,"ref":0.0000469},{"open":1.5e-7,"high":1.5e-7,"low":1.3e-7,"close":1.3e-7,"time":1681550761044,"volume":286.91999999999996,"ref":0.00004692},{"open":1.3e-7,"high":1.3e-7,"low":1.3e-7,"close":1.3e-7,"time":1681550821024,"volume":49.01,"ref":0.00004693},{"open":1.3e-7,"high":1.3e-7,"low":1.3e-7,"close":1.3e-7,"time":1681550881032,"volume":0,"ref":0.00004693},{"open":1.3e-7,"high":1.3e-7,"low":1.3e-7,"close":1.3e-7,"time":1681550941763,"volume":143.68,"ref":0.00004693},{"open":1.3e-7,"high":1.3e-7,"low":8e-8,"close":8e-8,"time":1681551001784,"volume":492.33,"ref":0.00004698},{"open":8e-8,"high":1.4e-7,"low":5e-8,"close":5e-8,"time":1681551061271,"volume":1326.53,"ref":0.00004695},{"open":5e-8,"high":1.4e-7,"low":5e-8,"close":1.2e-7,"time":1681551121276,"volume":1325.8,"ref":0.00004696},{"open":1.2e-7,"high":1.2e-7,"low":9e-8,"close":1e-7,"time":1681551181271,"volume":434.11999999999995,"ref":0.00004697},{"open":1e-7,"high":1.1e-7,"low":1e-7,"close":1.1e-7,"time":1681551241933,"volume":96.49,"ref":0.00004697},{"open":1.1e-7,"high":1.1e-7,"low":9e-8,"close":9e-8,"time":1681551301421,"volume":96.49,"ref":0.00004697},{"open":9e-8,"high":9e-8,"low":9e-8,"close":9e-8,"time":1681551361669,"volume":0,"ref":0.00004697},{"open":9e-8,"high":9e-8,"low":8e-8,"close":8e-8,"time":1681551421886,"volume":164.14,"ref":0.00004705},{"open":8e-8,"high":9e-8,"low":4e-8,"close":8e-8,"time":1681551481633,"volume":901.7099999999999,"ref":0.00004701},{"open":8e-8,"high":8e-8,"low":7e-8,"close":7e-8,"time":1681551541657,"volume":257.42,"ref":0.00004702},{"open":7e-8,"high":7e-8,"low":7e-8,"close":7e-8,"time":1681551601899,"volume":518.97,"ref":0.00004702},{"open":7e-8,"high":7e-8,"low":6e-8,"close":6e-8,"time":1681551662639,"volume":70.62,"ref":0.00004703},{"open":6e-8,"high":7e-8,"low":6e-8,"close":6e-8,"time":1681551721648,"volume":668.59,"ref":0.00004703},{"open":6e-8,"high":7e-8,"low":6e-8,"close":7e-8,"time":1681551781652,"volume":134.63,"ref":0.00004702},{"open":7e-8,"high":7e-8,"low":6e-8,"close":6e-8,"time":1681551842107,"volume":276.96000000000004,"ref":0.00004703},{"open":6e-8,"high":6e-8,"low":6e-8,"close":6e-8,"time":1681551902386,"volume":203.38,"ref":0.00004703},{"open":6e-8,"high":7e-8,"low":6e-8,"close":7e-8,"time":1681551962133,"volume":191.43,"ref":0.00004702},{"open":7e-8,"high":7e-8,"low":7e-8,"close":7e-8,"time":1681552022121,"volume":124.33,"ref":0.00004702},{"open":7e-8,"high":7e-8,"low":7e-8,"close":7e-8,"time":1681552082119,"volume":486.64000000000004,"ref":0.00004702},{"open":7e-8,"high":1.2e-7,"low":7e-8,"close":1.1e-7,"time":1681552142318,"volume":402.82000000000005,"ref":0.00004698},{"open":1.1e-7,"high":1.2e-7,"low":5e-8,"close":6e-8,"time":1681552202060,"volume":1476.88,"ref":0.00004703},{"open":6e-8,"high":6e-8,"low":6e-8,"close":6e-8,"time":1681552262057,"volume":0,"ref":0.00004703},{"open":6e-8,"high":6e-8,"low":6e-8,"close":6e-8,"time":1681552322064,"volume":0,"ref":0.00004703},{"open":6e-8,"high":8e-8,"low":6e-8,"close":7e-8,"time":1681552382780,"volume":270.94,"ref":0.00004701},{"open":7e-8,"high":7e-8,"low":7e-8,"close":7e-8,"time":1681552442286,"volume":326.22,"ref":0.00004701},{"open":7e-8,"high":8e-8,"low":7e-8,"close":7e-8,"time":1681552502268,"volume":255.82999999999998,"ref":0.00004701},{"open":7e-8,"high":7e-8,"low":7e-8,"close":7e-8,"time":1681552562536,"volume":0,"ref":0.00004701},{"open":7e-8,"high":8e-8,"low":7e-8,"close":8e-8,"time":1681552622769,"volume":116.19,"ref":0.00004701},{"open":8e-8,"high":8e-8,"low":8e-8,"close":8e-8,"time":1681552686017,"volume":0,"ref":0.00004701},{"open":8e-8,"high":1.5e-7,"low":5e-8,"close":1.4e-7,"time":1681552742509,"volume":825.3499999999999,"ref":0.00004693},{"open":1.4e-7,"high":1.4e-7,"low":1e-7,"close":1e-7,"time":1681552802748,"volume":628.96,"ref":0.00004695},{"open":1e-7,"high":1e-7,"low":9e-8,"close":9e-8,"time":1681552862744,"volume":164.49,"ref":0.00004696},{"open":9e-8,"high":1.7e-7,"low":7e-8,"close":1.4e-7,"time":1681552923050,"volume":1630.0200000000002,"ref":0.00004692},{"open":1.4e-7,"high":1.5e-7,"low":1.3e-7,"close":1.5e-7,"time":1681552982542,"volume":422.71999999999997,"ref":0.0000469},{"open":1.5e-7,"high":1.9e-7,"low":1.5e-7,"close":1.6e-7,"time":1681553042793,"volume":169.87,"ref":0.00004691},{"open":1.6e-7,"high":1.7e-7,"low":1.6e-7,"close":1.6e-7,"time":1681553103467,"volume":846.69,"ref":0.0000469},{"open":1.6e-7,"high":1.6e-7,"low":1e-7,"close":1e-7,"time":1681553162978,"volume":628.64,"ref":0.00004698},{"open":1e-7,"high":1.1e-7,"low":1e-7,"close":1.1e-7,"time":1681553222969,"volume":291.83000000000004,"ref":0.00004699},{"open":1.1e-7,"high":1.4e-7,"low":1.1e-7,"close":1.4e-7,"time":1681553283217,"volume":1743.17,"ref":0.0000469},{"open":1.4e-7,"high":1.4e-7,"low":1.4e-7,"close":1.4e-7,"time":1681553343466,"volume":0,"ref":0.0000469},{"open":1.4e-7,"high":1.4e-7,"low":1.2e-7,"close":1.3e-7,"time":1681553403467,"volume":191.41,"ref":0.00004692},{"open":1.3e-7,"high":1.5e-7,"low":1.3e-7,"close":1.4e-7,"time":1681553463218,"volume":258.88,"ref":0.00004692},{"open":1.4e-7,"high":1.4e-7,"low":1.2e-7,"close":1.2e-7,"time":1681553530678,"volume":368.66999999999996,"ref":0.00004694}]